{
  "generated_at": "2026-06-23T14:48:54",
  "today": "2026-06-23",
  "rule": "Ingreso(Action Task + Critical Path) - (Subs + Materiales + Additional) = Producido por trade, repartido entre los dias de ejecucion (cada dia suma a su semana Sat->Fri); sumado por semana por proyecto; menos fijos prorrateados = Produccion Neta.",
  "params": {
    "weekly_fixed": 18000.0,
    "window_start": "2026-05-02",
    "excluded": [
      "CANDACE - JUSTIN P REFERRAL",
      "Ginger Brown"
    ],
    "special_included": [
      "Brandy Sexton"
    ]
  },
  "totals": {
    "produced": 100209.81,
    "fixed": 144000.0,
    "net": -43790.19,
    "weeks": 8,
    "avg_weekly_net": -5473.77,
    "weeks_positive": 1,
    "weeks_negative": 7,
    "avg_weekly_produced": 12526.23
  },
  "timeline": [
    {
      "week_iso": "2026-W19",
      "week_start": "2026-05-02",
      "week_end": "2026-05-08",
      "produced": 11277.46,
      "fixed": 18000.0,
      "net": -6722.54,
      "cumulative_net": -6722.54,
      "active_count": 6,
      "active_projects": [
        "Brandy Sexton",
        "Clifford Clack",
        "Katie Holmes",
        "Lingyan Qiu",
        "Rohini Williams",
        "Stephanie Felton"
      ],
      "by_project": {
        "Stephanie Felton": 731.5,
        "Katie Holmes": 5757.73,
        "Clifford Clack": 2519.44,
        "Lingyan Qiu": 1802.39,
        "Rohini Williams": 656.93,
        "Brandy Sexton": -190.53
      }
    },
    {
      "week_iso": "2026-W20",
      "week_start": "2026-05-09",
      "week_end": "2026-05-15",
      "produced": 4541.68,
      "fixed": 18000.0,
      "net": -13458.32,
      "cumulative_net": -20180.86,
      "active_count": 6,
      "active_projects": [
        "Brandy Sexton",
        "Clifford Clack",
        "Katie Holmes",
        "Lingyan Qiu",
        "Rohini Williams",
        "Stephanie Felton"
      ],
      "by_project": {
        "Stephanie Felton": -668.5,
        "Katie Holmes": -4180.07,
        "Clifford Clack": 657.5,
        "Lingyan Qiu": 1087.39,
        "Rohini Williams": 2457.63,
        "Brandy Sexton": 5187.73
      }
    },
    {
      "week_iso": "2026-W21",
      "week_start": "2026-05-16",
      "week_end": "2026-05-22",
      "produced": 43733.32,
      "fixed": 18000.0,
      "net": 25733.32,
      "cumulative_net": 5552.46,
      "active_count": 7,
      "active_projects": [
        "Brandy Sexton",
        "Clifford Clack",
        "Katie Holmes",
        "Kyle Aubry",
        "Lingyan Qiu",
        "Rohini Williams",
        "Stephanie Felton"
      ],
      "by_project": {
        "Kyle Aubry": 21621.28,
        "Stephanie Felton": 917.87,
        "Katie Holmes": -6444.95,
        "Clifford Clack": 820.0,
        "Lingyan Qiu": 20343.21,
        "Rohini Williams": 2208.49,
        "Brandy Sexton": 4267.42
      }
    },
    {
      "week_iso": "2026-W22",
      "week_start": "2026-05-23",
      "week_end": "2026-05-29",
      "produced": 10469.8,
      "fixed": 18000.0,
      "net": -7530.2,
      "cumulative_net": -1977.74,
      "active_count": 7,
      "active_projects": [
        "Brandy Sexton",
        "Clifford Clack",
        "Katie Holmes",
        "Kyle Aubry",
        "Lingyan Qiu",
        "Rohini Williams",
        "Stephanie Felton"
      ],
      "by_project": {
        "Kyle Aubry": 830.0,
        "Stephanie Felton": 9610.48,
        "Lingyan Qiu": 5476.8,
        "Rohini Williams": 713.63,
        "Brandy Sexton": -6161.11
      }
    },
    {
      "week_iso": "2026-W23",
      "week_start": "2026-05-30",
      "week_end": "2026-06-05",
      "produced": 7847.02,
      "fixed": 18000.0,
      "net": -10152.98,
      "cumulative_net": -12130.72,
      "active_count": 7,
      "active_projects": [
        "Brandy Sexton",
        "Clifford Clack",
        "Katie Holmes",
        "Kyle Aubry",
        "Lingyan Qiu",
        "Rohini Williams",
        "Stephanie Felton"
      ],
      "by_project": {
        "Kyle Aubry": 2611.0,
        "Stephanie Felton": 4778.26,
        "Clifford Clack": 1115.73,
        "Lingyan Qiu": -772.9,
        "Rohini Williams": 713.63,
        "Brandy Sexton": -598.7
      }
    },
    {
      "week_iso": "2026-W24",
      "week_start": "2026-06-06",
      "week_end": "2026-06-12",
      "produced": 8138.96,
      "fixed": 18000.0,
      "net": -9861.04,
      "cumulative_net": -21991.76,
      "active_count": 6,
      "active_projects": [
        "Clifford Clack",
        "Katie Holmes",
        "Kyle Aubry",
        "Lingyan Qiu",
        "Rohini Williams",
        "Stephanie Felton"
      ],
      "by_project": {
        "Kyle Aubry": 1852.0,
        "Stephanie Felton": 3108.98,
        "Clifford Clack": 3918.88,
        "Lingyan Qiu": -1352.58,
        "Rohini Williams": 611.68
      }
    },
    {
      "week_iso": "2026-W25",
      "week_start": "2026-06-13",
      "week_end": "2026-06-19",
      "produced": 13590.53,
      "fixed": 18000.0,
      "net": -4409.47,
      "cumulative_net": -26401.23,
      "active_count": 6,
      "active_projects": [
        "Clifford Clack",
        "Katie Holmes",
        "Kyle Aubry",
        "Lingyan Qiu",
        "Rohini Williams",
        "Stephanie Felton"
      ],
      "by_project": {
        "Kyle Aubry": 865.0,
        "Stephanie Felton": 2481.98,
        "Clifford Clack": 7228.38,
        "Lingyan Qiu": 3015.17
      }
    },
    {
      "week_iso": "2026-W26",
      "week_start": "2026-06-20",
      "week_end": "2026-06-26",
      "produced": 611.04,
      "fixed": 18000.0,
      "net": -17388.96,
      "cumulative_net": -43790.19,
      "active_count": 6,
      "active_projects": [
        "Clifford Clack",
        "Katie Holmes",
        "Kyle Aubry",
        "Lingyan Qiu",
        "Rohini Williams",
        "Stephanie Felton"
      ],
      "by_project": {
        "Kyle Aubry": 1862.0,
        "Stephanie Felton": 2232.56,
        "Katie Holmes": -2500.0,
        "Clifford Clack": -210.62,
        "Lingyan Qiu": -772.9
      }
    }
  ],
  "by_project": [
    {
      "project": "Kyle Aubry",
      "revenue": 34512.0,
      "cost": 4870.72,
      "produced": 29641.28,
      "margin_pct": 85.9,
      "weeks": {
        "2026-W24": 1852.0,
        "2026-W21": 21621.28,
        "2026-W22": 830.0,
        "2026-W23": 2611.0,
        "2026-W25": 865.0,
        "2026-W26": 1862.0
      },
      "first_week": "2026-W21",
      "last_week": "2026-W26"
    },
    {
      "project": "Lingyan Qiu",
      "revenue": 72350.53,
      "cost": 43523.96,
      "produced": 28826.57,
      "margin_pct": 39.8,
      "weeks": {
        "2026-W23": -772.9,
        "2026-W24": -1352.58,
        "2026-W25": 3015.17,
        "2026-W26": -772.9,
        "2026-W21": 20343.21,
        "2026-W19": 1802.39,
        "2026-W20": 1087.39,
        "2026-W22": 5476.8
      },
      "first_week": "2026-W19",
      "last_week": "2026-W26"
    },
    {
      "project": "Stephanie Felton",
      "revenue": 47140.17,
      "cost": 23947.05,
      "produced": 23193.12,
      "margin_pct": 49.2,
      "weeks": {
        "2026-W20": -668.5,
        "2026-W21": 917.87,
        "2026-W22": 9610.48,
        "2026-W23": 4778.26,
        "2026-W19": 731.5,
        "2026-W24": 3108.98,
        "2026-W25": 2481.98,
        "2026-W26": 2232.56
      },
      "first_week": "2026-W19",
      "last_week": "2026-W26"
    },
    {
      "project": "Clifford Clack",
      "revenue": 33264.9,
      "cost": 17215.6,
      "produced": 16049.3,
      "margin_pct": 48.2,
      "weeks": {
        "2026-W26": -210.62,
        "2026-W23": 1115.73,
        "2026-W19": 2519.44,
        "2026-W20": 657.5,
        "2026-W25": 7228.38,
        "2026-W24": 3918.88,
        "2026-W21": 820.0
      },
      "first_week": "2026-W19",
      "last_week": "2026-W26"
    },
    {
      "project": "Rohini Williams",
      "revenue": 17662.0,
      "cost": 10300.0,
      "produced": 7362.0,
      "margin_pct": 41.7,
      "weeks": {
        "2026-W19": 656.93,
        "2026-W20": 2457.63,
        "2026-W21": 2208.49,
        "2026-W22": 713.63,
        "2026-W23": 713.63,
        "2026-W24": 611.68
      },
      "first_week": "2026-W19",
      "last_week": "2026-W24"
    },
    {
      "project": "Brandy Sexton",
      "revenue": 29880.0,
      "cost": 27375.18,
      "produced": 2504.82,
      "margin_pct": 8.4,
      "weeks": {
        "2026-W19": -190.53,
        "2026-W20": 5187.73,
        "2026-W21": 4267.42,
        "2026-W22": -6161.11,
        "2026-W23": -598.7
      },
      "first_week": "2026-W19",
      "last_week": "2026-W23"
    },
    {
      "project": "Katie Holmes",
      "revenue": 13939.69,
      "cost": 21306.98,
      "produced": -7367.29,
      "margin_pct": -52.9,
      "weeks": {
        "2026-W26": -2500.0,
        "2026-W19": 5757.73,
        "2026-W20": -4180.07,
        "2026-W21": -6444.95
      },
      "first_week": "2026-W19",
      "last_week": "2026-W26"
    }
  ],
  "by_pm": [
    {
      "pm": "Angel Pacheco",
      "produced": 37508.59,
      "revenue": 119555.12,
      "overhead": 69210.0,
      "net": -31701.41,
      "overhead_share_pct": 48.1,
      "projects": [
        "Clifford Clack",
        "Katie Holmes",
        "Lingyan Qiu"
      ],
      "margin_pct": 31.4,
      "weeks": {
        "2026-W26": -3483.52,
        "2026-W19": 10079.56,
        "2026-W20": -2435.18,
        "2026-W21": 14718.26,
        "2026-W23": 342.83,
        "2026-W25": 10243.55,
        "2026-W24": 2566.3,
        "2026-W22": 5476.8
      }
    },
    {
      "pm": "Milagros Porturas",
      "produced": 29641.28,
      "revenue": 34512.0,
      "overhead": 19978.86,
      "net": 9662.42,
      "overhead_share_pct": 13.9,
      "projects": [
        "Kyle Aubry"
      ],
      "margin_pct": 85.9,
      "weeks": {
        "2026-W24": 1852.0,
        "2026-W21": 21621.28,
        "2026-W22": 830.0,
        "2026-W23": 2611.0,
        "2026-W25": 865.0,
        "2026-W26": 1862.0
      }
    },
    {
      "pm": "Jeff",
      "produced": 23193.12,
      "revenue": 47140.17,
      "overhead": 27289.26,
      "net": -4096.14,
      "overhead_share_pct": 19.0,
      "projects": [
        "Stephanie Felton"
      ],
      "margin_pct": 49.2,
      "weeks": {
        "2026-W20": -668.5,
        "2026-W21": 917.87,
        "2026-W22": 9610.48,
        "2026-W23": 4778.26,
        "2026-W19": 731.5,
        "2026-W24": 3108.98,
        "2026-W25": 2481.98,
        "2026-W26": 2232.56
      }
    },
    {
      "pm": "Giselle Garcia",
      "produced": 9866.82,
      "revenue": 47542.0,
      "overhead": 27521.88,
      "net": -17655.06,
      "overhead_share_pct": 19.1,
      "projects": [
        "Brandy Sexton",
        "Rohini Williams"
      ],
      "margin_pct": 20.8,
      "weeks": {
        "2026-W19": 466.4,
        "2026-W20": 7645.36,
        "2026-W21": 6475.91,
        "2026-W22": -5447.48,
        "2026-W23": 114.93,
        "2026-W24": 611.68
      }
    }
  ],
  "data_quality": {
    "orphan_trades": 22,
    "orphan_cost": 45474.43,
    "priced_trades": 33,
    "total_trades": 56,
    "by_project": [
      {
        "project": "Brandy Sexton",
        "orphan_trades": 10,
        "orphan_cost": 18315.18,
        "examples": [
          {
            "trade": "DEMO INTERIOR",
            "cost": 650.0
          },
          {
            "trade": "ELECTRICAL ROUGH IN",
            "cost": 600.0
          },
          {
            "trade": "FRAMING",
            "cost": 520.98
          },
          {
            "trade": "PLUMBING ROUGH IN",
            "cost": 900.0
          },
          {
            "trade": "SHEETROCK",
            "cost": 600.0
          },
          {
            "trade": "COUNTERTOPS",
            "cost": 11491.7
          }
        ]
      },
      {
        "project": "Katie Holmes",
        "orphan_trades": 4,
        "orphan_cost": 14947.95,
        "examples": [
          {
            "trade": "INSULATION",
            "cost": 2500.0
          },
          {
            "trade": "PLUMBING ROUGH IN",
            "cost": 4947.95
          },
          {
            "trade": "ELECTRICAL ROUGH IN",
            "cost": 5500.0
          },
          {
            "trade": "MECHANICAL ROUGH IN",
            "cost": 2000.0
          }
        ]
      },
      {
        "project": "Lingyan Qiu",
        "orphan_trades": 1,
        "orphan_cost": 4250.97,
        "examples": [
          {
            "trade": "BRICKS & EXTERIOR SHEATING",
            "cost": 4250.97
          }
        ]
      },
      {
        "project": "Stephanie Felton",
        "orphan_trades": 2,
        "orphan_cost": 4250.0,
        "examples": [
          {
            "trade": "DOORS AND WINDOWS",
            "cost": 1400.0
          },
          {
            "trade": "COUNTERTOPS",
            "cost": 2850.0
          }
        ]
      },
      {
        "project": "Kyle Aubry",
        "orphan_trades": 2,
        "orphan_cost": 1900.0,
        "examples": [
          {
            "trade": "FRAMING: pony wall",
            "cost": 1000.0
          },
          {
            "trade": "EXTERIOR FINISHES (HARDIE, SIDING & TRIMS)",
            "cost": 900.0
          }
        ]
      },
      {
        "project": "Clifford Clack",
        "orphan_trades": 3,
        "orphan_cost": 1810.33,
        "examples": [
          {
            "trade": "ELECTRICAL TRIM",
            "cost": 498.27
          },
          {
            "trade": "FRAMING",
            "cost": 1062.06
          },
          {
            "trade": "PLUMBING",
            "cost": 250.0
          }
        ]
      }
    ],
    "note": "Trades con costo pero ingreso=$0 -> el producido real es un PISO, no techo. Cargar el ingreso por-trade (Action/Critical Path) cierra la fuga."
  },
  "brandy": {
    "project": "Brandy Sexton",
    "contract": 30975.0,
    "revenue_tasktree": 29880.0,
    "cost_tasktree": 27375.18,
    "cost_payments": 34839.0,
    "produced_tasktree": 2504.82,
    "produced_payments": -3864.0,
    "margin_tasktree_pct": 8.4,
    "margin_payments_pct": -12.5,
    "by_week": {
      "2026-W19": -190.53,
      "2026-W20": 5187.73,
      "2026-W21": 4267.41,
      "2026-W22": -6161.1,
      "2026-W23": -598.7
    },
    "active_weeks": [
      "2026-W19",
      "2026-W20",
      "2026-W21",
      "2026-W22",
      "2026-W23"
    ],
    "overhead_equal": 13714.29,
    "overhead_revwt": 8820.0,
    "net_equal_tasktree": -11209.47,
    "net_revwt_tasktree": -6315.18,
    "net_equal_payments": -17578.29,
    "net_revwt_payments": -12684.0,
    "allocation_detail": [
      {
        "week": "2026-W19",
        "active": 6,
        "equal": 3000.0,
        "revwt": 1881.8,
        "brandy_share_pct": 10.5
      },
      {
        "week": "2026-W20",
        "active": 6,
        "equal": 3000.0,
        "revwt": 1881.8,
        "brandy_share_pct": 10.5
      },
      {
        "week": "2026-W21",
        "active": 7,
        "equal": 2571.43,
        "revwt": 1685.47,
        "brandy_share_pct": 9.4
      },
      {
        "week": "2026-W22",
        "active": 7,
        "equal": 2571.43,
        "revwt": 1685.47,
        "brandy_share_pct": 9.4
      },
      {
        "week": "2026-W23",
        "active": 7,
        "equal": 2571.43,
        "revwt": 1685.47,
        "brandy_share_pct": 9.4
      }
    ],
    "trades": [
      {
        "project_id": "22PLKSsB4aeV",
        "project": "Brandy Sexton",
        "trade": "CABINETS",
        "revenue": 23900.0,
        "cost": 5710.0,
        "produced": 18190.0,
        "date": "2026-05-27",
        "start": "2026-05-06",
        "end": "2026-05-27"
      },
      {
        "project_id": "22PLKSsB4aeV",
        "project": "Brandy Sexton",
        "trade": "CABINET PAINTING",
        "revenue": 5980.0,
        "cost": 3350.0,
        "produced": 2630.0,
        "date": "2026-06-03",
        "start": "2026-05-19",
        "end": "2026-06-03"
      },
      {
        "project_id": "22PLKSsB4aeV",
        "project": "Brandy Sexton",
        "trade": "BASEBOARDS AND TRIM",
        "revenue": 0.0,
        "cost": 0,
        "produced": 0.0,
        "date": "2026-05-16",
        "start": "2026-05-16",
        "end": "2026-05-16"
      },
      {
        "project_id": "22PLKSsB4aeV",
        "project": "Brandy Sexton",
        "trade": "INTERIOR PAINT",
        "revenue": 0.0,
        "cost": 480.0,
        "produced": -480.0,
        "date": "2026-05-30",
        "start": "2026-05-28",
        "end": "2026-05-30"
      },
      {
        "project_id": "22PLKSsB4aeV",
        "project": "Brandy Sexton",
        "trade": "FRAMING",
        "revenue": 0.0,
        "cost": 520.98,
        "produced": -520.98,
        "date": "2026-05-05",
        "start": "2026-05-04",
        "end": "2026-05-05"
      },
      {
        "project_id": "22PLKSsB4aeV",
        "project": "Brandy Sexton",
        "trade": "ELECTRICAL ROUGH IN",
        "revenue": 0.0,
        "cost": 600.0,
        "produced": -600.0,
        "date": "2026-05-07",
        "start": "2026-05-06",
        "end": "2026-05-07"
      },
      {
        "project_id": "22PLKSsB4aeV",
        "project": "Brandy Sexton",
        "trade": "SHEETROCK",
        "revenue": 0.0,
        "cost": 600.0,
        "produced": -600.0,
        "date": "2026-05-13",
        "start": "2026-05-09",
        "end": "2026-05-13"
      },
      {
        "project_id": "22PLKSsB4aeV",
        "project": "Brandy Sexton",
        "trade": "DEMO INTERIOR",
        "revenue": 0.0,
        "cost": 650.0,
        "produced": -650.0,
        "date": "2026-05-02",
        "start": "2026-05-02",
        "end": "2026-05-02"
      },
      {
        "project_id": "22PLKSsB4aeV",
        "project": "Brandy Sexton",
        "trade": "WINDOWS",
        "revenue": 0.0,
        "cost": 741.35,
        "produced": -741.35,
        "date": "2026-05-16",
        "start": "2026-05-16",
        "end": "2026-05-16"
      },
      {
        "project_id": "22PLKSsB4aeV",
        "project": "Brandy Sexton",
        "trade": "PLUMBING ROUGH IN",
        "revenue": 0.0,
        "cost": 900.0,
        "produced": -900.0,
        "date": "2026-05-05",
        "start": "2026-05-05",
        "end": "2026-05-05"
      },
      {
        "project_id": "22PLKSsB4aeV",
        "project": "Brandy Sexton",
        "trade": "ELECTRICAL TRIM",
        "revenue": 0.0,
        "cost": 950.0,
        "produced": -950.0,
        "date": "2026-06-04",
        "start": "2026-05-26",
        "end": "2026-06-04"
      },
      {
        "project_id": "22PLKSsB4aeV",
        "project": "Brandy Sexton",
        "trade": "PLUMBING TRIM",
        "revenue": 0.0,
        "cost": 1381.15,
        "produced": -1381.15,
        "date": "2026-06-03",
        "start": "2026-05-25",
        "end": "2026-06-03"
      },
      {
        "project_id": "22PLKSsB4aeV",
        "project": "Brandy Sexton",
        "trade": "COUNTERTOPS",
        "revenue": 0.0,
        "cost": 11491.7,
        "produced": -11491.7,
        "date": "2026-05-29",
        "start": "2026-05-22",
        "end": "2026-05-29"
      }
    ]
  },
  "project_contracts": {
    "Kyle Aubry": 34512.0,
    "Stephanie Felton": 69492.0,
    "Katie Holmes": 44607.0,
    "Clifford Clack": 39627.0,
    "Martha Cockrell": 0,
    "Lingyan Qiu": 91880.0,
    "Rohini Williams": 19705.0,
    "Brandy Sexton": 30975.0
  }
}