{
  "date": "2026-03-30",
  "summary": {
    "overdue": 62,
    "blocked": 37,
    "active": 39,
    "coming": 127,
    "role_gaps": 209,
    "concern": "Gaurav Bansal (KU-1225Avondale) has 17 overdue + blocked tasks"
  },
  "pms": [
    {
      "name": "Angel Pacheco",
      "ov": 9,
      "act": 12,
      "proj": 2,
      "ind": "yellow"
    },
    {
      "name": "Jeff",
      "ov": 7,
      "act": 5,
      "proj": 4,
      "ind": "red"
    },
    {
      "name": "Marcio Oliveira",
      "ov": 8,
      "act": 3,
      "proj": 3,
      "ind": "red"
    },
    {
      "name": "Milagros Porturas",
      "ov": 10,
      "act": 7,
      "proj": 2,
      "ind": "red"
    }
  ],
  "projects": [
    {
      "name": "Ginger Brown",
      "pm": "Jeff, Milagros Porturas",
      "st": "issue",
      "c": {
        "ov": 11,
        "bl": 2,
        "ac": 5,
        "co": 5
      },
      "g": {
        "p": 10,
        "v": 14,
        "pc": 2
      },
      "tasks": {
        "overdue": [
          {
            "n": "MEETING WITH JONAS UPDATE QUOTE",
            "d": 6,
            "w": "\u26a0\ufe0f Nobody"
          },
          {
            "n": "MEETING WITH GINGER AND JONAS",
            "d": 4,
            "w": "Milagros Porturas"
          },
          {
            "n": "RECEIVE GINGER'S PAYMENT",
            "d": 3,
            "w": "\u26a0\ufe0f Nobody"
          },
          {
            "n": "DOORS AND WINDOWS: BILL & PAYMENT",
            "d": 3,
            "w": "\u26a0\ufe0f Nobody"
          },
          {
            "n": "SIDING: INSTALL SIDING",
            "d": 3,
            "w": "\u26a0\ufe0f Nobody"
          },
          {
            "n": "EXTERIOR PAINT: PAINT EXTERIOR",
            "d": 2,
            "w": "Milagros Porturas"
          },
          {
            "n": "SCHEDULE FOR CABINET PAINTER",
            "d": 2,
            "w": "Milagros Porturas"
          },
          {
            "n": "SCHEDULE SUB FOR PAINT",
            "d": 2,
            "w": "Milagros Porturas"
          },
          {
            "n": "SIDING: PM INSPECTION",
            "d": 2,
            "w": "Milagros Porturas"
          },
          {
            "n": "SIDING: COMPANYCAM COMPLETE",
            "d": 2,
            "w": "Milagros Porturas"
          },
          {
            "n": "SIDING: FINAL SIGN-OFF",
            "d": 2,
            "w": "Milagros Porturas"
          }
        ],
        "blocked": [
          {
            "n": "PLUMBING TRIM",
            "due": "04/13",
            "w": "Eliseo Vasquez, Milagros Porturas",
            "bl": "SCHEDULE PLUMBER (not started)"
          },
          {
            "n": "PLUMBING TRIM - INSPECTION",
            "due": "04/14",
            "w": "Milagros Porturas",
            "bl": "PLUMBING TRIM (not started)"
          }
        ],
        "active": [
          {
            "n": "EXTERIOR PAINT: PM INSPECTION",
            "dt": "Mar 30-30",
            "w": "Milagros Porturas"
          },
          {
            "n": "EXTERIOR PAINT: COMPANYCAM COMPLETE",
            "dt": "Mar 30-30",
            "w": "Milagros Porturas"
          },
          {
            "n": "EXTERIOR PAINT: FINAL SIGN-OFF",
            "dt": "Mar 30-30",
            "w": "Milagros Porturas"
          },
          {
            "n": "CABINETS - DOORS - SHELVES - WIP",
            "dt": "Mar 30-18",
            "w": "Milagros Porturas"
          },
          {
            "n": "Ginger's Confirmation of Materials",
            "dt": "Mar 30-4",
            "w": "\u26a0\ufe0f Nobody"
          }
        ],
        "coming": [
          {
            "n": "EXTERIOR PAINT: PM INSPECTION",
            "w": "Milagros Porturas",
            "when": "due today",
            "type": "due"
          },
          {
            "n": "EXTERIOR PAINT: COMPANYCAM COMPLETE",
            "w": "Milagros Porturas",
            "when": "due today",
            "type": "due"
          },
          {
            "n": "EXTERIOR PAINT: FINAL SIGN-OFF",
            "w": "Milagros Porturas",
            "when": "due today",
            "type": "due"
          },
          {
            "n": "CABINETS - DOORS - SHELVES - WIP",
            "w": "Milagros Porturas",
            "when": "starts today",
            "type": "starts"
          },
          {
            "n": "Ginger's Confirmation of Materials",
            "w": "\u26a0\ufe0f Nobody",
            "when": "starts today",
            "type": "starts"
          }
        ]
      }
    },
    {
      "name": "Gaurav Bansal (KU-1225Avondale)",
      "pm": "Jeff",
      "st": "issue",
      "c": {
        "ov": 10,
        "bl": 7,
        "ac": 1,
        "co": 20
      },
      "g": {
        "p": 29,
        "v": 16,
        "pc": 4
      },
      "tasks": {
        "overdue": [
          {
            "n": "CALL 811",
            "d": 10,
            "w": "\u26a0\ufe0f Nobody"
          },
          {
            "n": "Distribution plan Version 1",
            "d": 5,
            "w": "\u26a0\ufe0f Nobody"
          },
          {
            "n": "Initial project kick off meeting",
            "d": 5,
            "w": "Majo Roman, Jeff, Romina Rey, Planning | Claudia Delgado"
          },
          {
            "n": "Set of architectural final plans",
            "d": 5,
            "w": "\u26a0\ufe0f Nobody"
          },
          {
            "n": "811 INSPECTION",
            "d": 5,
            "w": "\u26a0\ufe0f Nobody"
          },
          {
            "n": "SCHEDULE DIG FOUNDATION AND PLUMBING DITCHES",
            "d": 5,
            "w": "\u26a0\ufe0f Nobody"
          },
          {
            "n": "MAKE SURE MATERIALS ARE ON SITE",
            "d": 4,
            "w": "\u26a0\ufe0f Nobody"
          },
          {
            "n": "Distribution plan Version 2",
            "d": 3,
            "w": "\u26a0\ufe0f Nobody"
          },
          {
            "n": "DIG FOUNDATION AND PLUMBING DITCHES",
            "d": 2,
            "w": "\u26a0\ufe0f Nobody"
          },
          {
            "n": "SCHEDULE FORM BOARD",
            "d": 2,
            "w": "\u26a0\ufe0f Nobody"
          }
        ],
        "blocked": [
          {
            "n": "INSPECTION - DIG FOUNDATION AND PLUMBING",
            "due": "03/30",
            "w": "\u26a0\ufe0f Nobody",
            "bl": "DIG FOUNDATION AND PLUMBING DITCHES (done)"
          },
          {
            "n": "PLACE FORM BOARD",
            "due": "04/02",
            "w": "\u26a0\ufe0f Nobody",
            "bl": "SCHEDULE FORM BOARD (not started)"
          },
          {
            "n": "INSPECTION - FORM BOARD",
            "due": "04/02",
            "w": "\u26a0\ufe0f Nobody",
            "bl": "PLACE FORM BOARD (done)"
          },
          {
            "n": "CITY INSPECTION - FORM BOARD",
            "due": "04/03",
            "w": "\u26a0\ufe0f Nobody",
            "bl": "PLACE FORM BOARD (done)"
          },
          {
            "n": "IN GROUND PLUMBING",
            "due": "04/06",
            "w": "\u26a0\ufe0f Nobody",
            "bl": "SCHEDULE - IN GROUND PLUMBING (not started)"
          },
          {
            "n": "INSPECTION - IN GROUND PLUMBING",
            "due": "04/07",
            "w": "\u26a0\ufe0f Nobody",
            "bl": "IN GROUND PLUMBING (done)"
          },
          {
            "n": "CITY INSPECTION - IN GROUND PLUMBING",
            "due": "04/08",
            "w": "\u26a0\ufe0f Nobody",
            "bl": "IN GROUND PLUMBING (done)"
          }
        ],
        "active": [
          {
            "n": "MATERIALS ON SITE",
            "dt": "Mar 30-30",
            "w": "\u26a0\ufe0f Nobody"
          }
        ],
        "coming": [
          {
            "n": "INSPECTION - DIG FOUNDATION AND PLUMBING",
            "w": "\u26a0\ufe0f Nobody",
            "when": "due today",
            "type": "due"
          },
          {
            "n": "MATERIALS ON SITE",
            "w": "\u26a0\ufe0f Nobody",
            "when": "due today",
            "type": "due"
          },
          {
            "n": "Distribution plan approved",
            "w": "\u26a0\ufe0f Nobody",
            "when": "due tomorrow",
            "type": "due"
          },
          {
            "n": "Structural plans",
            "w": "\u26a0\ufe0f Nobody",
            "when": "due tomorrow",
            "type": "due"
          },
          {
            "n": "Energy Report",
            "w": "\u26a0\ufe0f Nobody",
            "when": "due tomorrow",
            "type": "due"
          },
          {
            "n": "Sales finishes meeting with client report",
            "w": "Romina Rey",
            "when": "due tomorrow",
            "type": "due"
          },
          {
            "n": "Material List Draft",
            "w": "Romina Rey",
            "when": "due tomorrow",
            "type": "due"
          },
          {
            "n": "Version 1",
            "w": "\u26a0\ufe0f Nobody",
            "when": "due tomorrow",
            "type": "due"
          },
          {
            "n": "Version 2",
            "w": "\u26a0\ufe0f Nobody",
            "when": "due tomorrow",
            "type": "due"
          },
          {
            "n": "Change orders needed",
            "w": "\u26a0\ufe0f Nobody",
            "when": "due tomorrow",
            "type": "due"
          },
          {
            "n": "Final budget revised",
            "w": "\u26a0\ufe0f Nobody",
            "when": "due tomorrow",
            "type": "due"
          },
          {
            "n": "Final material list",
            "w": "Romina Rey",
            "when": "due Wed",
            "type": "due"
          },
          {
            "n": "Permit package compilation",
            "w": "Planning | Claudia Delgado",
            "when": "due Thu",
            "type": "due"
          },
          {
            "n": "Final Portfolio approved",
            "w": "\u26a0\ufe0f Nobody",
            "when": "due Thu",
            "type": "due"
          },
          {
            "n": "PLACE FORM BOARD",
            "w": "\u26a0\ufe0f Nobody",
            "when": "due Thu",
            "type": "due"
          },
          {
            "n": "INSPECTION - FORM BOARD",
            "w": "\u26a0\ufe0f Nobody",
            "when": "due Thu",
            "type": "due"
          },
          {
            "n": "SCHEDULE - IN GROUND PLUMBING",
            "w": "\u26a0\ufe0f Nobody",
            "when": "due Thu",
            "type": "due"
          },
          {
            "n": "VERIFY MATERIALS ON SITE",
            "w": "\u26a0\ufe0f Nobody",
            "when": "due Thu",
            "type": "due"
          },
          {
            "n": "SCHEDULE ELECTRICIAN",
            "w": "\u26a0\ufe0f Nobody",
            "when": "due Thu",
            "type": "due"
          },
          {
            "n": "VERIFY MATERIALS ON SITE",
            "w": "\u26a0\ufe0f Nobody",
            "when": "due Thu",
            "type": "due"
          }
        ]
      }
    },
    {
      "name": "Lingyan Qiu (CNG2025-458)",
      "pm": "Angel Pacheco, Jeff",
      "st": "issue",
      "c": {
        "ov": 10,
        "bl": 4,
        "ac": 8,
        "co": 17
      },
      "g": {
        "p": 7,
        "v": 20,
        "pc": 0
      },
      "tasks": {
        "overdue": [
          {
            "n": "FRAMING: CREATE SOW",
            "d": 4,
            "w": "Angel Pacheco"
          },
          {
            "n": "CONCRETE: CREATE SOW",
            "d": 4,
            "w": "Angel Pacheco"
          },
          {
            "n": "ELECTRICAL: BILL & PAYMENT",
            "d": 3,
            "w": "Brayan Ramos"
          },
          {
            "n": "RELOCATE MAIN PANEL: BILL & PAYMENT",
            "d": 3,
            "w": "Brayan Ramos"
          },
          {
            "n": "FRAMING: SOURCE VENDORS",
            "d": 3,
            "w": "Angel Pacheco"
          },
          {
            "n": "CONCRETE: SOURCE VENDORS",
            "d": 3,
            "w": "Angel Pacheco"
          },
          {
            "n": "PATIO: CREATE SOW",
            "d": 3,
            "w": "Angel Pacheco"
          },
          {
            "n": "CONCRETE: APPROVE WO",
            "d": 2,
            "w": "Angel Pacheco"
          },
          {
            "n": "PATIO: SOURCE VENDORS",
            "d": 2,
            "w": "Angel Pacheco"
          },
          {
            "n": "PATIO: CREATE SOW",
            "d": 2,
            "w": "Angel Pacheco"
          }
        ],
        "blocked": [
          {
            "n": "Foundation cure",
            "due": "04/06",
            "w": "Angel Pacheco",
            "bl": "Concrete pour - Foundation (not started)"
          },
          {
            "n": "FRAMING: FRAMING AND CORNICE",
            "due": "04/17",
            "w": "Angel Pacheco",
            "bl": "Foundation cure (done)"
          },
          {
            "n": "DOORS AND WINDOWS: INSTALL EXTERIOR DOORS AND WINDOWS",
            "due": "04/13",
            "w": "Angel Pacheco",
            "bl": "WINDOWS: CONFIRM DELIVERY (not started)"
          },
          {
            "n": "ELECTRICAL: ELECTRICAL ROUGH IN",
            "due": "04/18",
            "w": "Brayan Ramos, Angel Pacheco",
            "bl": "ELECTRICAL: CONFIRM SCHEDULE (not started)"
          }
        ],
        "active": [
          {
            "n": "Concrete pour - Foundation",
            "dt": "Mar 30-30",
            "w": "Angel Pacheco, Efren Aguirre"
          },
          {
            "n": "WINDOWS: PURCHASE MATERIAL",
            "dt": "Mar 30-30",
            "w": "Angel Pacheco, Romina Rey, Reynaldo Aquije"
          },
          {
            "n": "Rent porta potty",
            "dt": "Mar 30-30",
            "w": "Angel Pacheco"
          },
          {
            "n": "EXTERIOR DOORS: PURCHASE MATERIAL",
            "dt": "Mar 30-30",
            "w": "Romina Rey, Reynaldo Aquije"
          },
          {
            "n": "FRAMING: APPROVE WO",
            "dt": "Mar 30-30",
            "w": "Angel Pacheco"
          },
          {
            "n": "CONCRETE: CONFIRM SCHEDULE",
            "dt": "Mar 30-30",
            "w": "Angel Pacheco"
          },
          {
            "n": "PATIO: APPROVE WO",
            "dt": "Mar 30-30",
            "w": "Angel Pacheco"
          },
          {
            "n": "PATIO: SOURCE VENDORS",
            "dt": "Mar 30-30",
            "w": "Angel Pacheco"
          }
        ],
        "coming": [
          {
            "n": "Concrete pour - Foundation",
            "w": "Angel Pacheco, Efren Aguirre",
            "when": "due today",
            "type": "due"
          },
          {
            "n": "WINDOWS: PURCHASE MATERIAL",
            "w": "Angel Pacheco, Romina Rey, Reynaldo Aquije",
            "when": "due today",
            "type": "due"
          },
          {
            "n": "Rent porta potty",
            "w": "Angel Pacheco",
            "when": "due today",
            "type": "due"
          },
          {
            "n": "EXTERIOR DOORS: PURCHASE MATERIAL",
            "w": "Romina Rey, Reynaldo Aquije",
            "when": "due today",
            "type": "due"
          },
          {
            "n": "FRAMING: APPROVE WO",
            "w": "Angel Pacheco",
            "when": "due today",
            "type": "due"
          },
          {
            "n": "CONCRETE: CONFIRM SCHEDULE",
            "w": "Angel Pacheco",
            "when": "due today",
            "type": "due"
          },
          {
            "n": "PATIO: APPROVE WO",
            "w": "Angel Pacheco",
            "when": "due today",
            "type": "due"
          },
          {
            "n": "PATIO: SOURCE VENDORS",
            "w": "Angel Pacheco",
            "when": "due today",
            "type": "due"
          },
          {
            "n": "FOUNDATION: PM INSPECTION/CC REPORT",
            "w": "Angel Pacheco, Majo Roman",
            "when": "due tomorrow",
            "type": "due"
          },
          {
            "n": "DOORS AND WINDOWS: CREATE SOW",
            "w": "Angel Pacheco",
            "when": "due tomorrow",
            "type": "due"
          },
          {
            "n": "PATIO: CONFIRM SCHEDULE",
            "w": "Angel Pacheco",
            "when": "due tomorrow",
            "type": "due"
          },
          {
            "n": "PATIO: APPROVE WO",
            "w": "Angel Pacheco",
            "when": "due tomorrow",
            "type": "due"
          },
          {
            "n": "EXTERIOR SHEATHING: CREATE SOW",
            "w": "Angel Pacheco",
            "when": "due tomorrow",
            "type": "due"
          },
          {
            "n": "Foundation cure",
            "w": "Angel Pacheco",
            "when": "starts tomorrow",
            "type": "starts"
          },
          {
            "n": "CONCRETE: CUT THE CONCRETE",
            "w": "\u26a0\ufe0f Nobody",
            "when": "due Wed",
            "type": "due"
          },
          {
            "n": "PATIO: SUBFLOOR",
            "w": "\u26a0\ufe0f Nobody",
            "when": "due Thu",
            "type": "due"
          },
          {
            "n": "FRAMING: PURCHASE MATERIALS",
            "w": "Angel Pacheco, Romina Rey",
            "when": "due Thu",
            "type": "due"
          }
        ]
      }
    },
    {
      "name": "CANDACE - JUSTIN P REFERRAL (CNG2025-522)",
      "pm": "Marcio Oliveira",
      "st": "issue",
      "c": {
        "ov": 7,
        "bl": 3,
        "ac": 1,
        "co": 3
      },
      "g": {
        "p": 6,
        "v": 5,
        "pc": 0
      },
      "tasks": {
        "overdue": [
          {
            "n": "ROOFING: COMPELTE TAKEOFF",
            "d": 3,
            "w": "Marcio Oliveira, Romina Rey"
          },
          {
            "n": "ROOFING: APROVE WO",
            "d": 3,
            "w": "Marcio Oliveira"
          },
          {
            "n": "ROOFING: SUBMIT QUOTE",
            "d": 3,
            "w": "Marcio Oliveira"
          },
          {
            "n": "ROOFING: PURCHASE MATERIAL",
            "d": 2,
            "w": "Reynaldo Aquije, Romina Rey, Marjorie Serna"
          },
          {
            "n": "ROOFING: CONFIRM SCHEDULE",
            "d": 2,
            "w": "Marcio Oliveira"
          },
          {
            "n": "ROOFING: CREATE SOW",
            "d": 2,
            "w": "Marcio Oliveira"
          },
          {
            "n": "ROOFING: SECURE PRICING",
            "d": 2,
            "w": "\u26a0\ufe0f Nobody"
          }
        ],
        "blocked": [
          {
            "n": "ROOFING: CONFIRM DELIVERY",
            "due": "03/30",
            "w": "Romina Rey",
            "bl": "ROOFING: PURCHASE MATERIAL (not started)"
          },
          {
            "n": "ROOFING: INSTALL ROOFING",
            "due": "04/01",
            "w": "\u26a0\ufe0f Nobody",
            "bl": "ROOFING: CONFIRM DELIVERY (not started)"
          },
          {
            "n": "ROOFING: BILL & PAYMENT",
            "due": "04/10",
            "w": "\u26a0\ufe0f Nobody",
            "bl": "ROOFING: INSTALL ROOFING (not started)"
          }
        ],
        "active": [
          {
            "n": "AFTER FRAMING AND SHEATHING",
            "dt": "Mar 30-30",
            "w": "\u26a0\ufe0f Nobody"
          }
        ],
        "coming": [
          {
            "n": "ROOFING: CONFIRM DELIVERY",
            "w": "Romina Rey",
            "when": "due today",
            "type": "due"
          },
          {
            "n": "AFTER FRAMING AND SHEATHING",
            "w": "\u26a0\ufe0f Nobody",
            "when": "due today",
            "type": "due"
          },
          {
            "n": "ROOFING: INSTALL ROOFING",
            "w": "\u26a0\ufe0f Nobody",
            "when": "due Wed",
            "type": "due"
          }
        ]
      }
    },
    {
      "name": "Stephanie and Marc Felton",
      "pm": "Jeff, Marcio Oliveira",
      "st": "issue",
      "c": {
        "ov": 7,
        "bl": 1,
        "ac": 5,
        "co": 16
      },
      "g": {
        "p": 23,
        "v": 30,
        "pc": 0
      },
      "tasks": {
        "overdue": [
          {
            "n": "BRICKS: COMPLETE TAKEOFF",
            "d": 10,
            "w": "\u26a0\ufe0f Nobody"
          },
          {
            "n": "BRICKS: SECURE PRICING",
            "d": 4,
            "w": "\u26a0\ufe0f Nobody"
          },
          {
            "n": "INTERIOR DOORS AND TRIM: CONFIRM SCHEDULE",
            "d": 3,
            "w": "Marcio Oliveira, Jeff"
          },
          {
            "n": "INTERIOR DOORS: DELIVERY FEE PAYMENT",
            "d": 3,
            "w": "Romina Rey, Marjorie Serna"
          },
          {
            "n": "PLUMBING: BILL & PAYMENT",
            "d": 3,
            "w": "Eliseo Vasquez"
          },
          {
            "n": "BRICKS TIES: REQUEST CITY INSPECTION",
            "d": 2,
            "w": "\u26a0\ufe0f Nobody"
          },
          {
            "n": "INTERIOR DOORS: CONFIRM DELIVERY",
            "d": 2,
            "w": "Romina Rey"
          }
        ],
        "blocked": [
          {
            "n": "INTERIOR DOORS AND TRIM: INSTALL INTERIOR TRIM AND DOORS",
            "due": "04/03",
            "w": "\u26a0\ufe0f Nobody",
            "bl": "INTERIOR DOORS AND TRIM: CONFIRM SCHEDULE (not started)"
          }
        ],
        "active": [
          {
            "n": "DRYWALL: CONFIRM SCHEDULE",
            "dt": "Mar 30-31",
            "w": "Marcio Oliveira"
          },
          {
            "n": "INSULATION: CITY INSPECTION",
            "dt": "Mar 30-30",
            "w": "\u26a0\ufe0f Nobody"
          },
          {
            "n": "BRICKS TIES: CITY INSPECTION",
            "dt": "Mar 30-30",
            "w": "\u26a0\ufe0f Nobody"
          },
          {
            "n": "TRIM: COMPLETE TAKEOFF",
            "dt": "Mar 30-30",
            "w": "\u26a0\ufe0f Nobody"
          },
          {
            "n": "INSULATION: REQUEST BANK PAYMENT",
            "dt": "Mar 30-30",
            "w": "Jonas De Cardenas"
          }
        ],
        "coming": [
          {
            "n": "INSULATION: CITY INSPECTION",
            "w": "\u26a0\ufe0f Nobody",
            "when": "due today",
            "type": "due"
          },
          {
            "n": "BRICKS TIES: CITY INSPECTION",
            "w": "\u26a0\ufe0f Nobody",
            "when": "due today",
            "type": "due"
          },
          {
            "n": "TRIM: COMPLETE TAKEOFF",
            "w": "\u26a0\ufe0f Nobody",
            "when": "due today",
            "type": "due"
          },
          {
            "n": "INSULATION: REQUEST BANK PAYMENT",
            "w": "Jonas De Cardenas",
            "when": "due today",
            "type": "due"
          },
          {
            "n": "BRICKS: PURCHASE MATERIAL",
            "w": "Marcio Oliveira, Romina Rey, Reynaldo Aquije",
            "when": "due tomorrow",
            "type": "due"
          },
          {
            "n": "DRYWALL: CONFIRM SCHEDULE",
            "w": "Marcio Oliveira",
            "when": "due tomorrow",
            "type": "due"
          },
          {
            "n": "DRYWALL: PURCHASE MATERIAL",
            "w": "Romina Rey, Reynaldo Aquije",
            "when": "due tomorrow",
            "type": "due"
          },
          {
            "n": "DRYWALL: CONFIRM DELIVERY",
            "w": "Romina Rey",
            "when": "due tomorrow",
            "type": "due"
          },
          {
            "n": "TRIM: SECURE PRICING",
            "w": "\u26a0\ufe0f Nobody",
            "when": "due tomorrow",
            "type": "due"
          },
          {
            "n": "INTERIOR DOORS AND TRIM: INSTALL INTERIOR TRIM AND DOORS",
            "w": "\u26a0\ufe0f Nobody",
            "when": "starts Wed",
            "type": "starts"
          },
          {
            "n": "BRICKS: CONFIRM DELIVERY",
            "w": "Romina Rey",
            "when": "due Wed",
            "type": "due"
          },
          {
            "n": "DRYWALL: HANG SHEETROCK",
            "w": "\u26a0\ufe0f Nobody",
            "when": "starts Wed",
            "type": "starts"
          },
          {
            "n": "TRIM: PURCHASE MATERIAL",
            "w": "Romina Rey",
            "when": "due Wed",
            "type": "due"
          },
          {
            "n": "BRICKS: INSTALL BRICKS",
            "w": "\u26a0\ufe0f Nobody",
            "when": "starts Wed",
            "type": "starts"
          },
          {
            "n": "TRIM: CONFIRM DELIVERY",
            "w": "Romina Rey",
            "when": "due Thu",
            "type": "due"
          },
          {
            "n": "INSULATION: PAYMENT RECEIVED",
            "w": "\u26a0\ufe0f Nobody",
            "when": "due Thu",
            "type": "due"
          }
        ]
      }
    },
    {
      "name": "Sergio Lares (212129)",
      "pm": "Jeff, Milagros Porturas",
      "st": "issue",
      "c": {
        "ov": 4,
        "bl": 12,
        "ac": 4,
        "co": 19
      },
      "g": {
        "p": 13,
        "v": 16,
        "pc": 0
      },
      "tasks": {
        "overdue": [
          {
            "n": "ELECTRICAL: REQUEST CITY INSPECTION",
            "d": 7,
            "w": "Milagros Porturas"
          },
          {
            "n": "ELECTRICAL: CITY INSPECTION",
            "d": 6,
            "w": "Milagros Porturas"
          },
          {
            "n": "DEMO: BILL & PAYMENT",
            "d": 3,
            "w": "\u26a0\ufe0f Nobody"
          },
          {
            "n": "COUNTERTOPS: CONFIRM DELIVERY",
            "d": 3,
            "w": "Milagros Porturas, Romina Rey"
          }
        ],
        "blocked": [
          {
            "n": "PLUMBING: PLUMBING TRIM",
            "due": "04/01",
            "w": "Eliseo Vasquez",
            "bl": "PLUMBING: CONFIRM SCHEDULE (not started)"
          },
          {
            "n": "PLUMBING: PM INSPECTION / CC REPORT",
            "due": "04/02",
            "w": "Milagros Porturas",
            "bl": "PLUMBING: PLUMBING TRIM (not started)"
          },
          {
            "n": "ELECTRICAL: ELECTRICAL TRIM",
            "due": "04/01",
            "w": "Marcos Ayala",
            "bl": "ELECTRICAL: CONFIRM SCHEDULE (not started)"
          },
          {
            "n": "COUNTERTOPS: PM INSPECTION / CC REPORT",
            "due": "04/01",
            "w": "Milagros Porturas",
            "bl": "COUNTERTOPS: INSTALL COUNTERTOPS (not started)"
          },
          {
            "n": "APPLIANCES: INSTALL APPLIANCES",
            "due": "04/01",
            "w": "Milagros Porturas",
            "bl": "APPLIANCES: CONFIRM SCHEDULE (not started)"
          },
          {
            "n": "APPLIANCES: PM INSPECTION / CC REPORT",
            "due": "04/02",
            "w": "Milagros Porturas",
            "bl": "APPLIANCES: INSTALL APPLIANCES (not started)"
          },
          {
            "n": "CLEANING: FINAL CLEANING",
            "due": "04/04",
            "w": "\u26a0\ufe0f Nobody",
            "bl": "PUNCH LIST: WORK ON FINAL PUNCH LIST (not started)"
          },
          {
            "n": "CLEANING: PM INSPECTION / CC REPORT",
            "due": "04/04",
            "w": "Milagros Porturas",
            "bl": "CLEANING: FINAL CLEANING (not started)"
          },
          {
            "n": "PRE DELIVERY WALK THROUGH",
            "due": "03/31",
            "w": "Milagros Porturas",
            "bl": "SCHEDULE PRE DELIVERY WALK THROUGH WITH CLIENT (not started)"
          },
          {
            "n": "PUNCH LIST: CONFIRM SCHEDULE",
            "due": "04/01",
            "w": "Milagros Porturas",
            "bl": "PRE DELIVERY WALK THROUGH (not started)"
          },
          {
            "n": "PUNCH LIST: WORK ON FINAL PUNCH LIST",
            "due": "04/02",
            "w": "\u26a0\ufe0f Nobody",
            "bl": "PUNCH LIST: CONFIRM SCHEDULE (not started)"
          },
          {
            "n": "PROJECT DELIVERY",
            "due": "04/04",
            "w": "Milagros Porturas",
            "bl": "CLEANING: PM INSPECTION / CC REPORT (not started)"
          }
        ],
        "active": [
          {
            "n": "PLUMBING: CONFIRM SCHEDULE",
            "dt": "Mar 30-30",
            "w": "Eliseo Vasquez, Milagros Porturas"
          },
          {
            "n": "ELECTRICAL: CONFIRM SCHEDULE",
            "dt": "Mar 30-30",
            "w": "Milagros Porturas, Marcos Ayala"
          },
          {
            "n": "APPLIANCES: CONFIRM SCHEDULE",
            "dt": "Mar 30-30",
            "w": "Milagros Porturas"
          },
          {
            "n": "SCHEDULE PRE DELIVERY WALK THROUGH WITH CLIENT",
            "dt": "Mar 30-30",
            "w": "Milagros Porturas"
          }
        ],
        "coming": [
          {
            "n": "PLUMBING: CONFIRM SCHEDULE",
            "w": "Eliseo Vasquez, Milagros Porturas",
            "when": "due today",
            "type": "due"
          },
          {
            "n": "ELECTRICAL: CONFIRM SCHEDULE",
            "w": "Milagros Porturas, Marcos Ayala",
            "when": "due today",
            "type": "due"
          },
          {
            "n": "APPLIANCES: CONFIRM SCHEDULE",
            "w": "Milagros Porturas",
            "when": "due today",
            "type": "due"
          },
          {
            "n": "SCHEDULE PRE DELIVERY WALK THROUGH WITH CLIENT",
            "w": "Milagros Porturas",
            "when": "due today",
            "type": "due"
          },
          {
            "n": "COUNTERTOPS: INSTALL COUNTERTOPS",
            "w": "JC'S Countertops LLC, Milagros Porturas",
            "when": "due tomorrow",
            "type": "due"
          },
          {
            "n": "PRE DELIVERY WALK THROUGH",
            "w": "Milagros Porturas",
            "when": "due tomorrow",
            "type": "due"
          },
          {
            "n": "PLUMBING: PLUMBING TRIM",
            "w": "Eliseo Vasquez",
            "when": "due Wed",
            "type": "due"
          },
          {
            "n": "ELECTRICAL: ELECTRICAL TRIM",
            "w": "Marcos Ayala",
            "when": "due Wed",
            "type": "due"
          },
          {
            "n": "COUNTERTOPS: PM INSPECTION / CC REPORT",
            "w": "Milagros Porturas",
            "when": "due Wed",
            "type": "due"
          },
          {
            "n": "APPLIANCES: INSTALL APPLIANCES",
            "w": "Milagros Porturas",
            "when": "due Wed",
            "type": "due"
          },
          {
            "n": "PUNCH LIST: CONFIRM SCHEDULE",
            "w": "Milagros Porturas",
            "when": "due Wed",
            "type": "due"
          },
          {
            "n": "PLUMBING: BILL & PAYMENT",
            "w": "\u26a0\ufe0f Nobody",
            "when": "due Wed",
            "type": "due"
          },
          {
            "n": "CLEANING: CREATE SOW",
            "w": "Milagros Porturas",
            "when": "due Wed",
            "type": "due"
          },
          {
            "n": "PLUMBING: PM INSPECTION / CC REPORT",
            "w": "Milagros Porturas",
            "when": "due Thu",
            "type": "due"
          },
          {
            "n": "APPLIANCES: PM INSPECTION / CC REPORT",
            "w": "Milagros Porturas",
            "when": "due Thu",
            "type": "due"
          },
          {
            "n": "PUNCH LIST: WORK ON FINAL PUNCH LIST",
            "w": "\u26a0\ufe0f Nobody",
            "when": "due Thu",
            "type": "due"
          },
          {
            "n": "ELECTRICAL: PM INSPECTION / CC REPORT",
            "w": "\u26a0\ufe0f Nobody",
            "when": "due Thu",
            "type": "due"
          },
          {
            "n": "ELECTRICAL: BILL & PAYMENT",
            "w": "\u26a0\ufe0f Nobody",
            "when": "due Thu",
            "type": "due"
          },
          {
            "n": "CLEANING: SOURCE VENDOR",
            "w": "Milagros Porturas",
            "when": "due Thu",
            "type": "due"
          }
        ]
      }
    },
    {
      "name": "Katie Holmes & Sean Springs",
      "pm": "Jeff",
      "st": "issue",
      "c": {
        "ov": 4,
        "bl": 4,
        "ac": 2,
        "co": 10
      },
      "g": {
        "p": 9,
        "v": 34,
        "pc": 3
      },
      "tasks": {
        "overdue": [
          {
            "n": "DOORS AND WINDOWS: CONFIRM SCHEDULE",
            "d": 5,
            "w": "Jeff"
          },
          {
            "n": "FRAMING: CONFIRM SCHEDULE",
            "d": 4,
            "w": "Jeff"
          },
          {
            "n": "GARAGE DOOR: COMPLETE TAKEOFF",
            "d": 4,
            "w": "Jeff, Romina Rey"
          },
          {
            "n": "ASM MEETING WITH CLIENT",
            "d": 3,
            "w": "Jonas De Cardenas, Jeff"
          }
        ],
        "blocked": [
          {
            "n": "INSULATION: INSTALL INSULATION",
            "due": "04/07",
            "w": "\u26a0\ufe0f Nobody",
            "bl": "DOORS AND WINDOWS: LELAND INSTALL NEW WINDOWS (not started)"
          },
          {
            "n": "PLUMBING: PLUMBING ROUGH IN",
            "due": "04/14",
            "w": "Jeff",
            "bl": "PLUMBING: CONFIRM SCHEDULE (not started)"
          },
          {
            "n": "ELECTRICAL: ELECTRICAL ROUGH IN",
            "due": "04/20",
            "w": "Jeff",
            "bl": "PLUMBING: PLUMBING ROUGH IN (not started)"
          },
          {
            "n": "FRAMING: INTERIOR WALL FRAMING & BLOCKING",
            "due": "04/09",
            "w": "Jeff",
            "bl": "FRAMING: PURCHASE MATERIAL (not started)"
          }
        ],
        "active": [
          {
            "n": "DOORS AND WINDOWS: LELAND INSTALL NEW WINDOWS",
            "dt": "Mar 27-31",
            "w": "Jeff"
          },
          {
            "n": "GARAGE DOOR: ASM MEETING WITH CLIENT",
            "dt": "Mar 26-30",
            "w": "Jeff, Jonas De Cardenas"
          }
        ],
        "coming": [
          {
            "n": "GARAGE DOOR: ASM MEETING WITH CLIENT",
            "w": "Jeff, Jonas De Cardenas",
            "when": "due today",
            "type": "due"
          },
          {
            "n": "DOORS AND WINDOWS: LELAND INSTALL NEW WINDOWS",
            "w": "Jeff",
            "when": "due tomorrow",
            "type": "due"
          },
          {
            "n": "INSULATION: CREATE SOW",
            "w": "Jeff",
            "when": "due tomorrow",
            "type": "due"
          },
          {
            "n": "Purchase cabinets/vanities/counter tops",
            "w": "Jeff",
            "when": "starts Wed",
            "type": "starts"
          },
          {
            "n": "DOORS AND WINDOWS: PM INSPECTION / CC REPORT",
            "w": "Jeff",
            "when": "due Wed",
            "type": "due"
          },
          {
            "n": "INSULATION: SOURCE VENDORS",
            "w": "Jeff",
            "when": "due Wed",
            "type": "due"
          },
          {
            "n": "CABINETS: CREATE SOW",
            "w": "Jeff",
            "when": "due Wed",
            "type": "due"
          },
          {
            "n": "FRAMING: PURCHASE MATERIAL",
            "w": "Jeff, Reynaldo Aquije, Romina Rey",
            "when": "due Thu",
            "type": "due"
          },
          {
            "n": "INSULATION: APPROVE WO",
            "w": "Jeff",
            "when": "due Thu",
            "type": "due"
          },
          {
            "n": "CABINETS: SOURCE VENDORS",
            "w": "Jeff",
            "when": "due Thu",
            "type": "due"
          }
        ]
      }
    },
    {
      "name": "Martha Cockrell (CNG-20251199)",
      "pm": "Jeff, Marcio Oliveira",
      "st": "issue",
      "c": {
        "ov": 4,
        "bl": 0,
        "ac": 9,
        "co": 18
      },
      "g": {
        "p": 19,
        "v": 23,
        "pc": 2
      },
      "tasks": {
        "overdue": [
          {
            "n": "ROOFING: CONFIRM SCHEDULE FOR UNDERLAYMENT",
            "d": 4,
            "w": "Marcio Oliveira, Jeff"
          },
          {
            "n": "T-POLE: APPROVE WO",
            "d": 4,
            "w": "Marcio Oliveira"
          },
          {
            "n": "T-POLE: BUILD T-POLE",
            "d": 2,
            "w": "\u26a0\ufe0f Nobody"
          },
          {
            "n": "ROOFING: SECURE PRICING",
            "d": 2,
            "w": "\u26a0\ufe0f Nobody"
          }
        ],
        "blocked": [],
        "active": [
          {
            "n": "Relocate electrical to place TJI joists",
            "dt": "Mar 28-30",
            "w": "\u26a0\ufe0f Nobody"
          },
          {
            "n": "Relocate plumbing to place TJI joists",
            "dt": "Mar 30-31",
            "w": "\u26a0\ufe0f Nobody"
          },
          {
            "n": "ROOFING: INSTALL UNDERLAYMENT",
            "dt": "Mar 30-30",
            "w": "\u26a0\ufe0f Nobody"
          },
          {
            "n": "GARAGE DOOR: COMPLETE TAKEOFF",
            "dt": "Mar 30-30",
            "w": "\u26a0\ufe0f Nobody"
          },
          {
            "n": "T-POLE: REQUEST CITY INSPECTION",
            "dt": "Mar 30-30",
            "w": "Marcio Oliveira"
          },
          {
            "n": "SOLAR EQUIPMENT: CONFIRM REMOVAL",
            "dt": "Mar 30-30",
            "w": "Jeff"
          },
          {
            "n": "Solar panel relocation",
            "dt": "Mar 24-7",
            "w": "\u26a0\ufe0f Nobody"
          },
          {
            "n": "Electrical meter relocation",
            "dt": "Mar 24-7",
            "w": "\u26a0\ufe0f Nobody"
          },
          {
            "n": "FRAMING: PM INSPECTION / CC REPORT",
            "dt": "Mar 27-1",
            "w": "Jeff, Marcio Oliveira"
          }
        ],
        "coming": [
          {
            "n": "Relocate electrical to place TJI joists",
            "w": "\u26a0\ufe0f Nobody",
            "when": "due today",
            "type": "due"
          },
          {
            "n": "ROOFING: INSTALL UNDERLAYMENT",
            "w": "\u26a0\ufe0f Nobody",
            "when": "due today",
            "type": "due"
          },
          {
            "n": "GARAGE DOOR: COMPLETE TAKEOFF",
            "w": "\u26a0\ufe0f Nobody",
            "when": "due today",
            "type": "due"
          },
          {
            "n": "T-POLE: REQUEST CITY INSPECTION",
            "w": "Marcio Oliveira",
            "when": "due today",
            "type": "due"
          },
          {
            "n": "SOLAR EQUIPMENT: CONFIRM REMOVAL",
            "w": "Jeff",
            "when": "due today",
            "type": "due"
          },
          {
            "n": "GARAGE DOOR: PURCHASE MATERIAL",
            "w": "Romina Rey",
            "when": "due tomorrow",
            "type": "due"
          },
          {
            "n": "Relocate plumbing to place TJI joists",
            "w": "\u26a0\ufe0f Nobody",
            "when": "due tomorrow",
            "type": "due"
          },
          {
            "n": "T-POLE: CITY INSPECTION",
            "w": "\u26a0\ufe0f Nobody",
            "when": "due tomorrow",
            "type": "due"
          },
          {
            "n": "GARAGE DOOR: CONFIRM DELIVERY",
            "w": "\u26a0\ufe0f Nobody",
            "when": "due tomorrow",
            "type": "due"
          },
          {
            "n": "GARAGE DOOR: CREATE SOW",
            "w": "Marcio Oliveira, Jeff",
            "when": "due tomorrow",
            "type": "due"
          },
          {
            "n": "ROOFING: PURCHASE MATERIAL",
            "w": "\u26a0\ufe0f Nobody",
            "when": "due tomorrow",
            "type": "due"
          },
          {
            "n": "Relocate mechanical to place TJI joists",
            "w": "\u26a0\ufe0f Nobody",
            "when": "due Wed",
            "type": "due"
          },
          {
            "n": "T-POLE: RECONNECT T-POLE",
            "w": "Marcio Oliveira",
            "when": "due Wed",
            "type": "due"
          },
          {
            "n": "FRAMING: PURCHASE MATERIAL",
            "w": "Reynaldo Aquije, Romina Rey",
            "when": "due Wed",
            "type": "due"
          },
          {
            "n": "FRAMING: PM INSPECTION / CC REPORT",
            "w": "Jeff, Marcio Oliveira",
            "when": "due Wed",
            "type": "due"
          },
          {
            "n": "FRAMING: CONFIRM DELIVERY",
            "w": "\u26a0\ufe0f Nobody",
            "when": "due Wed",
            "type": "due"
          },
          {
            "n": "GARAGE DOOR: SOURCE VENDORS",
            "w": "Marcio Oliveira, Jeff",
            "when": "due Wed",
            "type": "due"
          },
          {
            "n": "GARAGE DOOR: APPROVE WO",
            "w": "Marcio Oliveira, Jeff",
            "when": "due Thu",
            "type": "due"
          }
        ]
      }
    },
    {
      "name": "Clifford Clack \u2014 Gym Addition",
      "pm": "Angel Pacheco, Jeff",
      "st": "issue",
      "c": {
        "ov": 3,
        "bl": 3,
        "ac": 4,
        "co": 18
      },
      "g": {
        "p": 7,
        "v": 21,
        "pc": 1
      },
      "tasks": {
        "overdue": [
          {
            "n": "DEPOSIT",
            "d": 75,
            "w": "\u26a0\ufe0f Nobody"
          },
          {
            "n": "AFTER PERMIT APPROVAL",
            "d": 58,
            "w": "\u26a0\ufe0f Nobody"
          },
          {
            "n": "FRAMING: CREATE SOW",
            "d": 3,
            "w": "Angel Pacheco"
          }
        ],
        "blocked": [
          {
            "n": "FRAMING: FRAMING AND CORNICE",
            "due": "04/10",
            "w": "Clifford Clack, Angel Pacheco",
            "bl": "Foundation cure (done)"
          },
          {
            "n": "FRAMING: PM INSPECTION / CC REPORT",
            "due": "04/13",
            "w": "Clifford Clack, Angel Pacheco",
            "bl": "FRAMING: FRAMING AND CORNICE (not started)"
          },
          {
            "n": "Foundation cure",
            "due": "04/07",
            "w": "Clifford Clack, Angel Pacheco",
            "bl": "Concrete pour (not started)"
          }
        ],
        "active": [
          {
            "n": "Concrete pour",
            "dt": "Mar 30-30",
            "w": "Clifford Clack, Angel Pacheco, Efren Aguirre"
          },
          {
            "n": "FRAMING: COMPLETE TAKE OFF",
            "dt": "Mar 26-30",
            "w": "Angel Pacheco, Romina Rey"
          },
          {
            "n": "FRAMING: SOURCE VENDORS",
            "dt": "Mar 28-30",
            "w": "Angel Pacheco"
          },
          {
            "n": "WINDOWS: COMPLETE TAKE OFF",
            "dt": "Mar 30-30",
            "w": "Angel Pacheco, Romina Rey"
          }
        ],
        "coming": [
          {
            "n": "Concrete pour",
            "w": "Clifford Clack, Angel Pacheco, Efren Aguirre",
            "when": "due today",
            "type": "due"
          },
          {
            "n": "FRAMING: COMPLETE TAKE OFF",
            "w": "Angel Pacheco, Romina Rey",
            "when": "due today",
            "type": "due"
          },
          {
            "n": "FRAMING: SOURCE VENDORS",
            "w": "Angel Pacheco",
            "when": "due today",
            "type": "due"
          },
          {
            "n": "WINDOWS: COMPLETE TAKE OFF",
            "w": "Angel Pacheco, Romina Rey",
            "when": "due today",
            "type": "due"
          },
          {
            "n": "PM INSPECTION | FOUNDATION",
            "w": "Clifford Clack, Angel Pacheco",
            "when": "due tomorrow",
            "type": "due"
          },
          {
            "n": "FRAMING: SECURE PRICING",
            "w": "Angel Pacheco, Romina Rey",
            "when": "due tomorrow",
            "type": "due"
          },
          {
            "n": "FRAMING: APPROVE WO",
            "w": "Angel Pacheco",
            "when": "due tomorrow",
            "type": "due"
          },
          {
            "n": "WINDOWS: SECURE PRICING",
            "w": "Angel Pacheco, Romina Rey",
            "when": "due tomorrow",
            "type": "due"
          },
          {
            "n": "DOORS: COMPLETE TAKE OFF",
            "w": "\u26a0\ufe0f Nobody",
            "when": "due tomorrow",
            "type": "due"
          },
          {
            "n": "Foundation cure",
            "w": "Clifford Clack, Angel Pacheco",
            "when": "starts tomorrow",
            "type": "starts"
          },
          {
            "n": "BRICKS: SAMPLES DELIVERY",
            "w": "Angel Pacheco, Romina Rey",
            "when": "starts tomorrow",
            "type": "starts"
          },
          {
            "n": "FRAMING: CONFIRM SCHEDULE",
            "w": "Angel Pacheco",
            "when": "due Wed",
            "type": "due"
          },
          {
            "n": "DOORS: SECURE PRICING",
            "w": "\u26a0\ufe0f Nobody",
            "when": "due Wed",
            "type": "due"
          },
          {
            "n": "FRAMING: PURCHASE MATERIAL",
            "w": "Angel Pacheco, Romina Rey",
            "when": "due Thu",
            "type": "due"
          },
          {
            "n": "WINDOWS: PURCHASE MATERIAL",
            "w": "Angel Pacheco, Romina Rey",
            "when": "due Thu",
            "type": "due"
          },
          {
            "n": "DOORS: PURCHASE MATERIALS",
            "w": "\u26a0\ufe0f Nobody",
            "when": "starts Thu",
            "type": "starts"
          },
          {
            "n": "ELECTRICAL: CONFIRM SCHEDULE",
            "w": "\u26a0\ufe0f Nobody",
            "when": "due Thu",
            "type": "due"
          },
          {
            "n": "MECHANICAL: CONFIRM SCHEDULE",
            "w": "Angel Pacheco",
            "when": "due Thu",
            "type": "due"
          }
        ]
      }
    },
    {
      "name": "Rohini Williams (CNG2025-496)",
      "pm": "Milagros Porturas",
      "st": "issue",
      "c": {
        "ov": 2,
        "bl": 1,
        "ac": 0,
        "co": 0
      },
      "g": {
        "p": 3,
        "v": 2,
        "pc": 0
      },
      "tasks": {
        "overdue": [
          {
            "n": "BASEBOARDS+DOORS: BILL & PAYMENT",
            "d": 3,
            "w": "\u26a0\ufe0f Nobody"
          },
          {
            "n": "DOORS AND WINDOWS: BILL & PAYMENT",
            "d": 3,
            "w": "\u26a0\ufe0f Nobody"
          }
        ],
        "blocked": [
          {
            "n": "811 INSPECTION",
            "due": "04/09",
            "w": "\u26a0\ufe0f Nobody",
            "bl": "CALL 811 (done)"
          }
        ],
        "active": [],
        "coming": []
      }
    },
    {
      "name": "Charles Harris \u2014 Argyle TX",
      "pm": "No PM",
      "st": "issue",
      "c": {
        "ov": 0,
        "bl": 0,
        "ac": 0,
        "co": 1
      },
      "g": {
        "p": 2,
        "v": 2,
        "pc": 0
      },
      "tasks": {
        "overdue": [],
        "blocked": [],
        "active": [],
        "coming": [
          {
            "n": "CIVIL AND GRADING PLANS",
            "w": "\u26a0\ufe0f Nobody",
            "when": "due Thu",
            "type": "due"
          }
        ]
      }
    },
    {
      "name": "Kyle Aubry - Project 01",
      "pm": "No PM",
      "st": "ok"
    }
  ]
}