{
  "week": "2026-W16",
  "period": "Apr 13 - Apr 18, 2026",
  "generated_at": "2026-04-13T07:33:54.346878",
  "summary": {
    "tasks_completed": 0,
    "on_time_rate": 0,
    "total_overdue_start": 41,
    "total_overdue_end": 21,
    "net_drift_days": 8,
    "direct_changes": 3,
    "cascade_changes": 0,
    "last_minute_changes": 3
  },
  "pm_performance": [
    {
      "name": "Angel Pacheco",
      "completed": 0,
      "on_time": 0,
      "late": 0,
      "avg_days_late": 0,
      "overdue_start_of_week": 10,
      "overdue_end_of_week": 4,
      "direct_changes": 0,
      "last_minute": 0,
      "projects": [
        "Clifford Clack \u2014 Gym Addition",
        "Lingyan Qiu (CNG2025-458)"
      ],
      "trend": "improving"
    },
    {
      "name": "Jeff",
      "completed": 0,
      "on_time": 0,
      "late": 0,
      "avg_days_late": 0,
      "overdue_start_of_week": 29,
      "overdue_end_of_week": 14,
      "direct_changes": 3,
      "last_minute": 3,
      "projects": [
        "Clifford Clack \u2014 Gym Addition",
        "Katie Holmes & Sean Springs",
        "Lingyan Qiu (CNG2025-458)",
        "Martha Cockrell (CNG-20251199)",
        "Sergio Lares (212129)",
        "Stephanie and Marc Felton"
      ],
      "trend": "improving"
    },
    {
      "name": "Marcio Oliveira",
      "completed": 0,
      "on_time": 0,
      "late": 0,
      "avg_days_late": 0,
      "overdue_start_of_week": 12,
      "overdue_end_of_week": 6,
      "direct_changes": 1,
      "last_minute": 1,
      "projects": [
        "CANDACE - JUSTIN P REFERRAL (CNG2025-522)",
        "Martha Cockrell (CNG-20251199)",
        "Stephanie and Marc Felton"
      ],
      "trend": "improving"
    },
    {
      "name": "Milagros Porturas",
      "completed": 0,
      "on_time": 0,
      "late": 0,
      "avg_days_late": 0,
      "overdue_start_of_week": 12,
      "overdue_end_of_week": 7,
      "direct_changes": 0,
      "last_minute": 0,
      "projects": [
        "Ginger Brown",
        "Sergio Lares (212129)"
      ],
      "trend": "improving"
    }
  ],
  "projects": [
    {
      "name": "CANDACE - JUSTIN P REFERRAL (CNG2025-522)",
      "pm": "Marcio Oliveira",
      "week_summary": "",
      "completed_this_week": [],
      "still_overdue": [
        "ROOFING: APROVE WO",
        "ROOFING: SUBMIT QUOTE"
      ],
      "schedule_changes": [],
      "drift_days": 0,
      "forecast_next_2_weeks": [
        {
          "task": "FRAMING: BILL & PAYMENT",
          "due": "Apr 13",
          "risk": "high",
          "note": "No assignee"
        },
        {
          "task": "ROOFING: CONFIRM SCHEDULE",
          "due": "Apr 13",
          "risk": "high",
          "note": "Blocked by: ROOFING: APROVE WO"
        },
        {
          "task": "AFTER FRAMING AND SHEATHING",
          "due": "Apr 13",
          "risk": "high",
          "note": "No assignee"
        },
        {
          "task": "FINAL PAYMENT",
          "due": "Apr 14",
          "risk": "high",
          "note": "No assignee"
        },
        {
          "task": "ROOFING: SECURE PRICING",
          "due": "Apr 15",
          "risk": "high",
          "note": "No assignee"
        },
        {
          "task": "ROOFING: INSTALL ROOFING",
          "due": "Apr 20",
          "risk": "high",
          "note": "Blocked + no assignee"
        },
        {
          "task": "ROOFING: BILL & PAYMENT",
          "due": "Apr 21",
          "risk": "high",
          "note": "No assignee"
        },
        {
          "task": "ROOFING: PURCHASE MATERIAL",
          "due": "Apr 15",
          "risk": "medium",
          "note": "Depends on: ROOFING: SECURE PRICING"
        },
        {
          "task": "ROOFING: CONFIRM DELIVERY",
          "due": "Apr 16",
          "risk": "medium",
          "note": "Depends on: ROOFING: PURCHASE MATERIAL"
        },
        {
          "task": "ROOFING: COMPELTE TAKEOFF",
          "due": "Apr 14",
          "risk": "low",
          "note": "On track"
        },
        {
          "task": "ROOFING: CREATE SOW",
          "due": "Apr 14",
          "risk": "low",
          "note": "On track"
        }
      ]
    },
    {
      "name": "Clifford Clack \u2014 Gym Addition",
      "pm": "Angel Pacheco, Jeff",
      "week_summary": "",
      "completed_this_week": [],
      "still_overdue": [
        "FRAMING: CONFIRM SCHEDULE"
      ],
      "schedule_changes": [],
      "drift_days": 0,
      "forecast_next_2_weeks": [
        {
          "task": "FOUNDATION: BILL & PAYMENT",
          "due": "Apr 13",
          "risk": "high",
          "note": "No assignee"
        },
        {
          "task": "ELECTRICAL: CONFIRM SCHEDULE",
          "due": "Apr 13",
          "risk": "high",
          "note": "No assignee"
        },
        {
          "task": "BRICKS: APPROVE WO",
          "due": "Apr 13",
          "risk": "high",
          "note": "No assignee"
        },
        {
          "task": "Concrete Income 1",
          "due": "Apr 13",
          "risk": "high",
          "note": "No assignee"
        },
        {
          "task": "FRAMING: FRAMING AND CORNICE",
          "due": "Apr 14",
          "risk": "high",
          "note": "Blocked by: FRAMING: CONFIRM SCHEDULE"
        },
        {
          "task": "FRAMING: CONFIRM DELIVERY",
          "due": "Apr 14",
          "risk": "high",
          "note": "No assignee"
        },
        {
          "task": "FRAMING: PM INSPECTION / CC REPORT",
          "due": "Apr 15",
          "risk": "high",
          "note": "Blocked by: FRAMING: FRAMING AND CORNICE"
        },
        {
          "task": "ROOF DECKING: SECURE PRICING",
          "due": "Apr 16",
          "risk": "high",
          "note": "No assignee"
        },
        {
          "task": "BRICKS: CONFIRM SCHEDULE",
          "due": "Apr 20",
          "risk": "high",
          "note": "No assignee"
        },
        {
          "task": "ROOFING: DECKING",
          "due": "Apr 21",
          "risk": "high",
          "note": "No assignee"
        },
        {
          "task": "MECHANICAL: BILL & PAYMENT",
          "due": "Apr 24",
          "risk": "high",
          "note": "No assignee"
        },
        {
          "task": "FRAMING: PURCHASE MATERIAL",
          "due": "Apr 13",
          "risk": "low",
          "note": "On track"
        },
        {
          "task": "MECHANICAL: CONFIRM SCHEDULE",
          "due": "Apr 13",
          "risk": "low",
          "note": "On track"
        },
        {
          "task": "BRICK: PURCHASE MATERIAL",
          "due": "Apr 14",
          "risk": "low",
          "note": "On track"
        },
        {
          "task": "MECHANICAL: MINI SPLIT",
          "due": "Apr 14",
          "risk": "low",
          "note": "On track"
        },
        {
          "task": "BRICK: CONFIRM DELIVERY",
          "due": "Apr 15",
          "risk": "low",
          "note": "On track"
        },
        {
          "task": "ELECTRICAL: ROUGH IN",
          "due": "Apr 15",
          "risk": "low",
          "note": "On track"
        },
        {
          "task": "MECHANICAL: PM INSPECTION / CC REPORT",
          "due": "Apr 15",
          "risk": "low",
          "note": "On track"
        },
        {
          "task": "ROOF DECKING: COMPLETE TAKEOFF",
          "due": "Apr 15",
          "risk": "low",
          "note": "On track"
        },
        {
          "task": "ROOFING: CREATE SOW",
          "due": "Apr 15",
          "risk": "low",
          "note": "On track"
        },
        {
          "task": "EXTERIOR SHEATHING: INSTALLATION",
          "due": "Apr 16",
          "risk": "low",
          "note": "On track"
        },
        {
          "task": "ELECTRICAL: PM INSPECTION / CC REPORT",
          "due": "Apr 16",
          "risk": "low",
          "note": "On track"
        },
        {
          "task": "ROOFING: SOURCE VENDORS",
          "due": "Apr 16",
          "risk": "low",
          "note": "On track"
        },
        {
          "task": "EXTERIOR SHEATHING: PM INSPECTION",
          "due": "Apr 17",
          "risk": "low",
          "note": "On track"
        },
        {
          "task": "ROOF DECKING: PURCHASE MATERIAL",
          "due": "Apr 17",
          "risk": "low",
          "note": "On track"
        },
        {
          "task": "ROOFING: APPROVE WO",
          "due": "Apr 17",
          "risk": "low",
          "note": "On track"
        },
        {
          "task": "ROOFING: CONFIRM SCHEDULE",
          "due": "Apr 18",
          "risk": "low",
          "note": "On track"
        },
        {
          "task": "ROOF DECKING: CONFIRM DELIVERY",
          "due": "Apr 22",
          "risk": "low",
          "note": "On track"
        },
        {
          "task": "DOORS AND WINDOWS: INSTALL DOORS AND WINDOWS",
          "due": "Apr 23",
          "risk": "low",
          "note": "On track"
        },
        {
          "task": "ELECTRICAL: BILL & PAYMENT",
          "due": "Apr 24",
          "risk": "low",
          "note": "On track"
        },
        {
          "task": "BRICK: BRICK TIES",
          "due": "Apr 27",
          "risk": "low",
          "note": "On track"
        },
        {
          "task": "ROOFING: INSTALL SHINGLES",
          "due": "Apr 27",
          "risk": "low",
          "note": "On track"
        },
        {
          "task": "FRAMING: BILL & PAYMENT",
          "due": "Apr 27",
          "risk": "low",
          "note": "On track"
        },
        {
          "task": "INSULATION: CREATE SOW",
          "due": "Apr 27",
          "risk": "low",
          "note": "On track"
        },
        {
          "task": "RUBBER FLOORING: COMPLETE TAKEOFF",
          "due": "Apr 27",
          "risk": "low",
          "note": "On track"
        }
      ]
    },
    {
      "name": "Ginger Brown",
      "pm": "Milagros Porturas",
      "week_summary": "",
      "completed_this_week": [],
      "still_overdue": [
        "PLUMBING: CONFIRM SCHEDULE",
        "MATERIALS: GINGER'S CONFIRMATION",
        "CABINETS: APPROVE WO",
        "ELECTRICAL: CONFIRM SCHEDULE",
        "CABINETS: CONFIRM SCHEDULE"
      ],
      "schedule_changes": [
        {
          "task": "ELECTRICAL TRIM: PURCHASE MATERIAL",
          "shift": "+3d",
          "type": "last-minute"
        },
        {
          "task": "ELECTRICAL TRIM: CONFIRM DELIVERY",
          "shift": "+3d",
          "type": "last-minute"
        }
      ],
      "drift_days": 6,
      "forecast_next_2_weeks": [
        {
          "task": "PAINT PORCH: COMPLETE TAKEOFF",
          "due": "Apr 13",
          "risk": "high",
          "note": "No assignee"
        },
        {
          "task": "PAINT PORCH: SECURE PRICING",
          "due": "Apr 13",
          "risk": "high",
          "note": "No assignee"
        },
        {
          "task": "SIDING: INSTALL SIDING & EXTERIOR PAINT",
          "due": "Apr 14",
          "risk": "high",
          "note": "No assignee"
        },
        {
          "task": "ELECTRICAL TRIM: CONFIRM DELIVERY",
          "due": "Apr 14",
          "risk": "high",
          "note": "No assignee"
        },
        {
          "task": "PLUMBING: PLUMBING TRIM",
          "due": "Apr 15",
          "risk": "high",
          "note": "Blocked by: PLUMBING: CONFIRM SCHEDULE"
        },
        {
          "task": "PLUMBING TRIM: CONFIRM DELIVERY (TOILETS)",
          "due": "Apr 15",
          "risk": "high",
          "note": "No assignee"
        },
        {
          "task": "CABINETS: BILL & PAYMENT",
          "due": "Apr 15",
          "risk": "high",
          "note": "No assignee"
        },
        {
          "task": "PLUMBING: PM INSPECTION / CC REPORT",
          "due": "Apr 16",
          "risk": "high",
          "note": "Blocked by: PLUMBING: PLUMBING TRIM"
        },
        {
          "task": "SIDING: BILL & PAYMENT",
          "due": "Apr 16",
          "risk": "high",
          "note": "No assignee"
        },
        {
          "task": "APPLIANCES: INSTALL APPLIANCES",
          "due": "Apr 17",
          "risk": "high",
          "note": "No assignee"
        },
        {
          "task": "SIDING: BILL & PAYMENT",
          "due": "Apr 17",
          "risk": "high",
          "note": "No assignee"
        },
        {
          "task": "ELECTRICAL: ELECTRICAL TRIM",
          "due": "Apr 18",
          "risk": "high",
          "note": "Blocked by: ELECTRICAL TRIM: CONFIRM DELIVERY, ELECTRICAL: CONFIRM SCHEDULE"
        },
        {
          "task": "PLUMBING: CITY INSPECTION",
          "due": "Apr 18",
          "risk": "high",
          "note": "No assignee"
        },
        {
          "task": "CABINETS: BILL & PAYMENT",
          "due": "Apr 18",
          "risk": "high",
          "note": "No assignee"
        },
        {
          "task": "MECHANICAL: MECHANICAL TRIM",
          "due": "Apr 20",
          "risk": "high",
          "note": "Blocked + no assignee"
        },
        {
          "task": "ELECTRICAL: PM INSPECTION / CC REPORT",
          "due": "Apr 20",
          "risk": "high",
          "note": "Blocked by: ELECTRICAL: ELECTRICAL TRIM"
        },
        {
          "task": "ELECTRICAL: MAIN PANEL CONNECTION",
          "due": "Apr 20",
          "risk": "high",
          "note": "No assignee"
        },
        {
          "task": "MECHANICAL: PM INSPECTION / CC REPORT",
          "due": "Apr 21",
          "risk": "high",
          "note": "Blocked by: MECHANICAL: MECHANICAL TRIM"
        },
        {
          "task": "POOL: REMODEL POOL",
          "due": "Apr 21",
          "risk": "high",
          "note": "No assignee"
        },
        {
          "task": "PLUMBING: BILL & PAYMENT",
          "due": "Apr 21",
          "risk": "high",
          "note": "No assignee"
        },
        {
          "task": "MECHANICAL: CITY INSPECTION",
          "due": "Apr 22",
          "risk": "high",
          "note": "No assignee"
        },
        {
          "task": "CABINETS: PAINT SHELVES & BASEBOARDS",
          "due": "Apr 22",
          "risk": "high",
          "note": "No assignee"
        },
        {
          "task": "APPLIANCES: BILL & PAYMENT",
          "due": "Apr 24",
          "risk": "high",
          "note": "No assignee"
        },
        {
          "task": "CABINETS: BILL & PAYMENT",
          "due": "Apr 24",
          "risk": "high",
          "note": "No assignee"
        },
        {
          "task": "GLASS: TAKE MEASUREMENTS",
          "due": "Apr 25",
          "risk": "high",
          "note": "No assignee"
        },
        {
          "task": "INTERIOR PAINT: TOUCH UPS",
          "due": "Apr 27",
          "risk": "high",
          "note": "No assignee"
        },
        {
          "task": "ELECTRICAL: BILL & PAYMENT",
          "due": "Apr 27",
          "risk": "high",
          "note": "No assignee"
        },
        {
          "task": "PLUMBING TRIM: PURCHASE MATERIAL (TOILETS)",
          "due": "Apr 13",
          "risk": "low",
          "note": "On track"
        },
        {
          "task": "APPLIANCES: CONFIRM SCHEDULE",
          "due": "Apr 13",
          "risk": "low",
          "note": "On track"
        },
        {
          "task": "INTERIOR PAINT: PURCHASE MATERIAL",
          "due": "Apr 13",
          "risk": "low",
          "note": "On track"
        },
        {
          "task": "ELECTRICAL TRIM: PURCHASE MATERIAL",
          "due": "Apr 14",
          "risk": "low",
          "note": "On track"
        },
        {
          "task": "PAINT PORCH: CREATE SOW",
          "due": "Apr 14",
          "risk": "low",
          "note": "On track"
        },
        {
          "task": "PAINT PORCH: PURCHASE MATERIAL",
          "due": "Apr 14",
          "risk": "low",
          "note": "On track"
        },
        {
          "task": "INTERIOR PAINT: CONFIRM DELIVERY",
          "due": "Apr 14",
          "risk": "low",
          "note": "On track"
        },
        {
          "task": "MECHANICAL: CONFIRM SCHEDULE",
          "due": "Apr 15",
          "risk": "low",
          "note": "On track"
        },
        {
          "task": "GUTTERS: CREATE SOW",
          "due": "Apr 15",
          "risk": "low",
          "note": "On track"
        },
        {
          "task": "SIDING: PM INSPECTION / CC REPORT",
          "due": "Apr 15",
          "risk": "low",
          "note": "On track"
        },
        {
          "task": "PORCH: SOURCE VENDORS",
          "due": "Apr 15",
          "risk": "low",
          "note": "On track"
        },
        {
          "task": "INTERIOT PAINT: CREATE SOW",
          "due": "Apr 15",
          "risk": "low",
          "note": "On track"
        },
        {
          "task": "GUTTERS: SOURCE VENDORS",
          "due": "Apr 16",
          "risk": "low",
          "note": "On track"
        },
        {
          "task": "POOL: CONFIRM SCHEDULE",
          "due": "Apr 16",
          "risk": "low",
          "note": "On track"
        },
        {
          "task": "INTERIOR PAINT: SOURCE VENDORS",
          "due": "Apr 16",
          "risk": "low",
          "note": "On track"
        },
        {
          "task": "PLUMBING: REQUEST CITY INSPECTION",
          "due": "Apr 17",
          "risk": "low",
          "note": "On track"
        },
        {
          "task": "PORCH: APPROVE WO",
          "due": "Apr 17",
          "risk": "low",
          "note": "On track"
        },
        {
          "task": "GUTTERS: APPROVE WO",
          "due": "Apr 17",
          "risk": "low",
          "note": "On track"
        },
        {
          "task": "INTERIOR PAINT: APPROVE WO",
          "due": "Apr 17",
          "risk": "low",
          "note": "On track"
        },
        {
          "task": "CABINETS: PAINT CABINETS, DOORS, STAIRS",
          "due": "Apr 18",
          "risk": "low",
          "note": "On track"
        },
        {
          "task": "APPLIANCES: PM INSPECTION / CC REPORT",
          "due": "Apr 18",
          "risk": "low",
          "note": "On track"
        },
        {
          "task": "PORCH: CONFIRM SCHEDULE",
          "due": "Apr 18",
          "risk": "low",
          "note": "On track"
        },
        {
          "task": "GUTTERS: CONFIRM SCHEDULE",
          "due": "Apr 18",
          "risk": "low",
          "note": "On track"
        },
        {
          "task": "PAINT PORCH: CONFIRM DELIVERY",
          "due": "Apr 18",
          "risk": "low",
          "note": "On track"
        },
        {
          "task": "INTERIOR PAINT: CONFIRM SCHEDULE",
          "due": "Apr 18",
          "risk": "low",
          "note": "On track"
        },
        {
          "task": "CABINETS: PM INSPECTION / CC REPORT",
          "due": "Apr 20",
          "risk": "low",
          "note": "On track"
        },
        {
          "task": "DELIVERY: CONFIRM PRE DELIVERY WALK",
          "due": "Apr 20",
          "risk": "low",
          "note": "On track"
        },
        {
          "task": "MECHANICAL: REQUEST CITY INSPECTION",
          "due": "Apr 21",
          "risk": "low",
          "note": "On track"
        },
        {
          "task": "DELIVERY: PRE WALK THROUGH",
          "due": "Apr 21",
          "risk": "low",
          "note": "On track"
        },
        {
          "task": "GLASS: CREATE SOW",
          "due": "Apr 21",
          "risk": "low",
          "note": "On track"
        },
        {
          "task": "ELECTRICAL: CONNECT POWER TO THE HOUSE",
          "due": "Apr 21",
          "risk": "low",
          "note": "On track"
        },
        {
          "task": "REQUEST FINAL BUILDING INSPECTION",
          "due": "Apr 22",
          "risk": "low",
          "note": "On track"
        },
        {
          "task": "GLASS: SOURCE VENDORS",
          "due": "Apr 22",
          "risk": "low",
          "note": "On track"
        },
        {
          "task": "POOL: PM INSPECTION / CC REPORT",
          "due": "Apr 22",
          "risk": "low",
          "note": "On track"
        },
        {
          "task": "ELECTRICAL: REQUEST CITY INSPECTION",
          "due": "Apr 23",
          "risk": "low",
          "note": "On track"
        },
        {
          "task": "FINAL BUILDING INSPECTION",
          "due": "Apr 23",
          "risk": "low",
          "note": "On track"
        },
        {
          "task": "CLEANING: CONFIRM SCHEDULE",
          "due": "Apr 23",
          "risk": "low",
          "note": "On track"
        },
        {
          "task": "GLASS: APPROVE WO",
          "due": "Apr 23",
          "risk": "low",
          "note": "On track"
        },
        {
          "task": "PORCH: PAINT PORCH",
          "due": "Apr 24",
          "risk": "low",
          "note": "On track"
        },
        {
          "task": "GLASS: CONFIRM SCHEDULE",
          "due": "Apr 24",
          "risk": "low",
          "note": "On track"
        },
        {
          "task": "ELECTRICAL: CITY INSPECTION",
          "due": "Apr 24",
          "risk": "low",
          "note": "On track"
        },
        {
          "task": "GUTTERS: GUTTER INSTALLATION",
          "due": "Apr 27",
          "risk": "low",
          "note": "On track"
        },
        {
          "task": "CLEANING: FINAL CLEANING",
          "due": "Apr 27",
          "risk": "low",
          "note": "On track"
        },
        {
          "task": "PORCH: PM INSPECTION / CC REPORT",
          "due": "Apr 27",
          "risk": "low",
          "note": "On track"
        }
      ]
    },
    {
      "name": "Katie Holmes & Sean Springs",
      "pm": "Jeff",
      "week_summary": "",
      "completed_this_week": [],
      "still_overdue": [
        "FRAMING: CONFIRM SCHEDULE",
        "DOORS AND WINDOWS: LELAND INSTALL NEW WINDOWS",
        "DOORS AND WINDOWS: PM INSPECTION / CC REPORT",
        "GARAGE DOOR: ASM MEETING WITH CLIENT"
      ],
      "schedule_changes": [],
      "drift_days": 0,
      "forecast_next_2_weeks": [
        {
          "task": "GARAGE DOOR: PURCHASE MATERIAL",
          "due": "Apr 17",
          "risk": "high",
          "note": "No assignee"
        },
        {
          "task": "FRAMING: INTERIOR WALL FRAMING & BLOCKING",
          "due": "Apr 18",
          "risk": "high",
          "note": "Blocked by: FRAMING: PURCHASE MATERIAL, DOORS AND WINDOWS: LELAND INSTALL NEW WINDOWS"
        },
        {
          "task": "FRAMING: CONFIRM DELIVERY",
          "due": "Apr 13",
          "risk": "low",
          "note": "On track"
        },
        {
          "task": "GARAGE DOOR: CONFIRM DELIVERY",
          "due": "Apr 17",
          "risk": "low",
          "note": "On track"
        },
        {
          "task": "FRAMING: PM INSPECTION / CC REPORT",
          "due": "Apr 20",
          "risk": "low",
          "note": "On track"
        },
        {
          "task": "FRAMING: REQUEST CITY INSPECTION",
          "due": "Apr 21",
          "risk": "low",
          "note": "On track"
        },
        {
          "task": "FRAMING: CITY INSPECTION",
          "due": "Apr 22",
          "risk": "low",
          "note": "On track"
        },
        {
          "task": "PLUMBING: CREATE SOW",
          "due": "Apr 23",
          "risk": "low",
          "note": "On track"
        },
        {
          "task": "PLUMBING: SOURCE VENDORS",
          "due": "Apr 24",
          "risk": "low",
          "note": "On track"
        },
        {
          "task": "PLUMBING: APPROVE WO",
          "due": "Apr 25",
          "risk": "low",
          "note": "On track"
        },
        {
          "task": "INTERIOR DOORS: COMPLETE TAKEOFF",
          "due": "Apr 27",
          "risk": "low",
          "note": "On track"
        },
        {
          "task": "PLUMBING: CONFIRM SCHEDULE",
          "due": "Apr 27",
          "risk": "low",
          "note": "On track"
        }
      ]
    },
    {
      "name": "Lingyan Qiu (CNG2025-458)",
      "pm": "Angel Pacheco, Jeff",
      "week_summary": "",
      "completed_this_week": [],
      "still_overdue": [
        "FOUNDATION: FOUNDATION CURE",
        "FOUNDATION: RENT A PORTA POTTY",
        "FRAMING: CONFIRM SCHEDULE"
      ],
      "schedule_changes": [],
      "drift_days": 0,
      "forecast_next_2_weeks": [
        {
          "task": "CONCRETE POUR: BILL & PAYMENT",
          "due": "Apr 13",
          "risk": "high",
          "note": "No assignee"
        },
        {
          "task": "ELECTRICAL: ELECTRICAL ROUGH IN",
          "due": "Apr 18",
          "risk": "high",
          "note": "Blocked by: ELECTRICAL: CONFIRM SCHEDULE"
        },
        {
          "task": "TILES: CONFIRM SCHEDULE",
          "due": "Apr 21",
          "risk": "high",
          "note": "Blocked by: TILES: APPROVE WO"
        },
        {
          "task": "INSULATION: CONFIRM SCHEDULE",
          "due": "Apr 22",
          "risk": "high",
          "note": "Blocked by: INSULATION: APPROVE WO"
        },
        {
          "task": "FRAMING: FRAMING AND CORNICE",
          "due": "Apr 24",
          "risk": "high",
          "note": "Blocked by: FOUNDATION: FOUNDATION CURE, FRAMING: CONFIRM DELIVERY"
        },
        {
          "task": "PLUMBING: PLUMBING ROUGH IN",
          "due": "Apr 24",
          "risk": "high",
          "note": "Blocked by: PLUMBING: CONFIRM SCHEDULE, PLUMBING: CONFIRM DELIVERY"
        },
        {
          "task": "INSULATION: INSTALL INSULATION",
          "due": "Apr 24",
          "risk": "high",
          "note": "Blocked + no assignee"
        },
        {
          "task": "INSULATION: PM INSPECTION / CC REPORT",
          "due": "Apr 25",
          "risk": "high",
          "note": "Blocked by: INSULATION: CONFIRM SCHEDULE, INSULATION: INSTALL INSULATION"
        },
        {
          "task": "INSULATION: REQUEST CITY INSPECTION",
          "due": "Apr 25",
          "risk": "high",
          "note": "No assignee"
        },
        {
          "task": "DOORS AND WINDOWS: INSTALL EXTERIOR DOORS AND WINDOWS",
          "due": "Apr 27",
          "risk": "high",
          "note": "Blocked by: WINDOWS: CONFIRM DELIVERY, DOORS AND WINDOWS: CONFIRM SCHEDULE"
        },
        {
          "task": "FRAMING: BILL & PAYMENT",
          "due": "Apr 27",
          "risk": "high",
          "note": "No assignee"
        },
        {
          "task": "INSULATION: CITY INSPECTION",
          "due": "Apr 27",
          "risk": "high",
          "note": "No assignee"
        },
        {
          "task": "WINDOWS: PURCHASE MATERIAL",
          "due": "Apr 13",
          "risk": "low",
          "note": "On track"
        },
        {
          "task": "EXTERIOR DOORS: PURCHASE MATERIAL",
          "due": "Apr 13",
          "risk": "low",
          "note": "On track"
        },
        {
          "task": "FRAMING: CONFIRM DELIVERY",
          "due": "Apr 13",
          "risk": "low",
          "note": "On track"
        },
        {
          "task": "ELECTRICAL: CONFIRM SCHEDULE",
          "due": "Apr 14",
          "risk": "low",
          "note": "On track"
        },
        {
          "task": "MECHANICAL: CONFIRM SCHEDULE",
          "due": "Apr 16",
          "risk": "low",
          "note": "On track"
        },
        {
          "task": "PLUMBING: CONFIRM SCHEDULE",
          "due": "Apr 16",
          "risk": "low",
          "note": "On track"
        },
        {
          "task": "INSULATION: CREATE SOW",
          "due": "Apr 17",
          "risk": "low",
          "note": "On track"
        },
        {
          "task": "MECHANICAL: MECHANICAL ROUGH IN",
          "due": "Apr 18",
          "risk": "low",
          "note": "On track"
        },
        {
          "task": "FRAMING: REQUEST CITY INSPECTION",
          "due": "Apr 18",
          "risk": "low",
          "note": "On track"
        },
        {
          "task": "INSULATION: SOURCE VENDORS",
          "due": "Apr 18",
          "risk": "low",
          "note": "On track"
        },
        {
          "task": "ELECTRICAL: PM INSPECTION / CC REPORT",
          "due": "Apr 20",
          "risk": "low",
          "note": "On track"
        },
        {
          "task": "FRAMING: CITY INSPECTION",
          "due": "Apr 20",
          "risk": "low",
          "note": "On track"
        },
        {
          "task": "INSULATION: APPROVE WO",
          "due": "Apr 20",
          "risk": "low",
          "note": "On track"
        },
        {
          "task": "DRYWALL: CREATE SOW",
          "due": "Apr 21",
          "risk": "low",
          "note": "On track"
        },
        {
          "task": "DRYWALL: SOURCE VENDORS",
          "due": "Apr 22",
          "risk": "low",
          "note": "On track"
        },
        {
          "task": "DRYWALL: APPROVE WO",
          "due": "Apr 23",
          "risk": "low",
          "note": "On track"
        },
        {
          "task": "WINDOWS: CONFIRM DELIVERY",
          "due": "Apr 24",
          "risk": "low",
          "note": "On track"
        },
        {
          "task": "DRYWALL: CONFIRM SCHEDULE",
          "due": "Apr 24",
          "risk": "low",
          "note": "On track"
        },
        {
          "task": "PLUMBING: PM INSPECTION / CC REPORT",
          "due": "Apr 25",
          "risk": "low",
          "note": "On track"
        },
        {
          "task": "FRAMING: PM INSPECTION / CC REPORT",
          "due": "Apr 25",
          "risk": "low",
          "note": "On track"
        }
      ]
    },
    {
      "name": "Martha Cockrell (CNG-20251199)",
      "pm": "Jeff, Marcio Oliveira",
      "week_summary": "",
      "completed_this_week": [],
      "still_overdue": [
        "FRAMING: FRAMING AND CORNICE",
        "DOORS AND WINDOWS: CREATE SOW"
      ],
      "schedule_changes": [],
      "drift_days": 0,
      "forecast_next_2_weeks": [
        {
          "task": "FRAMING: CONFIRM DELIVERY",
          "due": "Apr 13",
          "risk": "high",
          "note": "No assignee"
        },
        {
          "task": "EXTERIOR DOORS & WINDOWS: CONFIRM DELIVERY (EXTERIOR DOORS)",
          "due": "Apr 15",
          "risk": "high",
          "note": "No assignee"
        },
        {
          "task": "DOORS AND WINDOWS: INSTALL EXTERIOR DOORS AND WINDOWS",
          "due": "Apr 18",
          "risk": "high",
          "note": "No assignee"
        },
        {
          "task": "FRAMING: CITY INSPECTION",
          "due": "Apr 21",
          "risk": "high",
          "note": "No assignee"
        },
        {
          "task": "DOORS AND WINDOWS: PROTECT DOORS AND WINDOWS",
          "due": "Apr 22",
          "risk": "high",
          "note": "No assignee"
        },
        {
          "task": "EXTERIOR SHEATHING: INSTALL TAPE",
          "due": "Apr 22",
          "risk": "high",
          "note": "No assignee"
        },
        {
          "task": "DEMO: DEMO ROOF",
          "due": "Apr 23",
          "risk": "high",
          "note": "No assignee"
        },
        {
          "task": "FRAMING: BILL & PAYMENT",
          "due": "Apr 24",
          "risk": "high",
          "note": "No assignee"
        },
        {
          "task": "GARAGE DOOR: COMPLETE TAKEOFF",
          "due": "Apr 24",
          "risk": "high",
          "note": "No assignee"
        },
        {
          "task": "FRAMING: INSTALL TJI JOISTS",
          "due": "Apr 25",
          "risk": "high",
          "note": "No assignee"
        },
        {
          "task": "GARAGE DOOR: CONFIRM DELIVERY",
          "due": "Apr 27",
          "risk": "high",
          "note": "No assignee"
        },
        {
          "task": "FRAMING: PM INSPECTION / CC REPORT",
          "due": "Apr 13",
          "risk": "low",
          "note": "On track"
        },
        {
          "task": "DOORS AND WINDOWS: SOURCE VENDORS",
          "due": "Apr 13",
          "risk": "low",
          "note": "On track"
        },
        {
          "task": "EXTERIOR SHEATHING: CONFIRM SCHEDULE FOR TAPE INSTALLATION",
          "due": "Apr 13",
          "risk": "low",
          "note": "On track"
        },
        {
          "task": "EXTERIOR DOORS & WINDOWS: PURCHASE MATERIAL (EXTERIOR DOORS)",
          "due": "Apr 14",
          "risk": "low",
          "note": "On track"
        },
        {
          "task": "FRAMING: REQUEST CITY INSPECTION",
          "due": "Apr 14",
          "risk": "low",
          "note": "On track"
        },
        {
          "task": "DOORS AND WINDOWS: APPROVE WO",
          "due": "Apr 14",
          "risk": "low",
          "note": "On track"
        },
        {
          "task": "DOORS AND WINDOWS: CONFIRM SCHEDULE",
          "due": "Apr 15",
          "risk": "low",
          "note": "On track"
        },
        {
          "task": "EXTERIOR SHEATHING: PM INSPECTION / CC REPORT",
          "due": "Apr 23",
          "risk": "low",
          "note": "On track"
        },
        {
          "task": "DOORS AND WINDOWS: PM INSPECTION / CC REPORT",
          "due": "Apr 23",
          "risk": "low",
          "note": "On track"
        },
        {
          "task": "GARAGE DOOR: CREATE SOW",
          "due": "Apr 23",
          "risk": "low",
          "note": "On track"
        },
        {
          "task": "GARAGE DOOR: SOURCE VENDORS",
          "due": "Apr 24",
          "risk": "low",
          "note": "On track"
        },
        {
          "task": "GARAGE DOOR: PURCHASE MATERIAL",
          "due": "Apr 25",
          "risk": "low",
          "note": "On track"
        },
        {
          "task": "GARAGE DOOR: APPROVE WO",
          "due": "Apr 25",
          "risk": "low",
          "note": "On track"
        },
        {
          "task": "GARAGE DOOR: CONFIRM SCHEDULE",
          "due": "Apr 27",
          "risk": "low",
          "note": "On track"
        }
      ]
    },
    {
      "name": "Sergio Lares (212129)",
      "pm": "Jeff, Milagros Porturas",
      "week_summary": "",
      "completed_this_week": [],
      "still_overdue": [
        "PUNCH LIST: INSTALL CABINET",
        "PUNCH LIST: FIX DISHWASHER"
      ],
      "schedule_changes": [],
      "drift_days": 0,
      "forecast_next_2_weeks": [
        {
          "task": "COUNTERTOPS: BILL & PAYMENT",
          "due": "Apr 13",
          "risk": "high",
          "note": "No assignee"
        },
        {
          "task": "ELECTRICAL: BILL & PAYMENT",
          "due": "Apr 13",
          "risk": "high",
          "note": "No assignee"
        },
        {
          "task": "PUNCH LIST: PM INSPECTION / CC REPORT",
          "due": "Apr 13",
          "risk": "low",
          "note": "On track"
        }
      ]
    },
    {
      "name": "Stephanie and Marc Felton",
      "pm": "Jeff, Marcio Oliveira",
      "week_summary": "",
      "completed_this_week": [],
      "still_overdue": [
        "DOORS AND WINDOWS: REQUEST BANK PAYMENT",
        "INSULATION: REQUEST BANK PAYMENT"
      ],
      "schedule_changes": [
        {
          "task": "DRYWALL: PURCHASE MATERIAL",
          "shift": "+2d",
          "type": "last-minute"
        }
      ],
      "drift_days": 2,
      "forecast_next_2_weeks": [
        {
          "task": "INSULATION: BILL & PAYMENT",
          "due": "Apr 13",
          "risk": "high",
          "note": "No assignee"
        },
        {
          "task": "INSULATION: PAYMENT RECEIVED",
          "due": "Apr 14",
          "risk": "high",
          "note": "No assignee"
        },
        {
          "task": "FLOORING: COMPLETE TAKEOFF (BASEBOARDS)",
          "due": "Apr 20",
          "risk": "high",
          "note": "No assignee"
        },
        {
          "task": "DRYWALL: HANG SHEETROCK",
          "due": "Apr 21",
          "risk": "high",
          "note": "No assignee"
        },
        {
          "task": "FLOORING & CARPET: SECURE PRICING (BASEBOARDS)",
          "due": "Apr 21",
          "risk": "high",
          "note": "No assignee"
        },
        {
          "task": "INTERIOR PAINT: PAINT WALLS & CEILING",
          "due": "Apr 24",
          "risk": "high",
          "note": "Blocked + no assignee"
        },
        {
          "task": "INTERIOR DOORS AND TRIM: BILL & PAYMENT",
          "due": "Apr 24",
          "risk": "high",
          "note": "No assignee"
        },
        {
          "task": "FLOORING: CONFIRM DELIVERY (BASEBOARDS)",
          "due": "Apr 24",
          "risk": "high",
          "note": "No assignee"
        },
        {
          "task": "DRYWALL: TAPE, BED & TEXTURE",
          "due": "Apr 25",
          "risk": "high",
          "note": "No assignee"
        },
        {
          "task": "FLOORING: CONFIRM DELIVERY",
          "due": "Apr 25",
          "risk": "high",
          "note": "No assignee"
        },
        {
          "task": "INTERIOR PAINT: BILL & PAYMENT",
          "due": "Apr 27",
          "risk": "high",
          "note": "No assignee"
        },
        {
          "task": "DRYWALL: BILL & PAYMENT",
          "due": "Apr 27",
          "risk": "high",
          "note": "No assignee"
        },
        {
          "task": "DRYWALL: CONFIRM SCHEDULE",
          "due": "Apr 13",
          "risk": "low",
          "note": "On track"
        },
        {
          "task": "DRYWALL: PURCHASE MATERIAL",
          "due": "Apr 13",
          "risk": "low",
          "note": "On track"
        },
        {
          "task": "INTERIOR DOORS AND TRIM: PM INSPECTION / CC REPORT",
          "due": "Apr 14",
          "risk": "low",
          "note": "On track"
        },
        {
          "task": "DRYWALL: CONFIRM DELIVERY",
          "due": "Apr 15",
          "risk": "low",
          "note": "On track"
        },
        {
          "task": "INTERIOR PAINT: CREATE SOW",
          "due": "Apr 15",
          "risk": "low",
          "note": "On track"
        },
        {
          "task": "INTERIOR PAINT: SOURCE VENDORS",
          "due": "Apr 16",
          "risk": "low",
          "note": "On track"
        },
        {
          "task": "INTERIOR PAINT: APPROVE WO",
          "due": "Apr 17",
          "risk": "low",
          "note": "On track"
        },
        {
          "task": "INTERIOR PAINT: CONFIRM SCHEDULE",
          "due": "Apr 18",
          "risk": "low",
          "note": "On track"
        },
        {
          "task": "FLOORING: COMPLETE TAKEOFF",
          "due": "Apr 18",
          "risk": "low",
          "note": "On track"
        },
        {
          "task": "BRICKS: CONFIRM DELIVERY",
          "due": "Apr 20",
          "risk": "low",
          "note": "On track"
        },
        {
          "task": "FLOORING: SECURE PRICING",
          "due": "Apr 20",
          "risk": "low",
          "note": "On track"
        },
        {
          "task": "CARPET: COMPLETE TAKEOFF",
          "due": "Apr 20",
          "risk": "low",
          "note": "On track"
        },
        {
          "task": "INTERIOR PAINT: CONFIRM DELIVERY",
          "due": "Apr 21",
          "risk": "low",
          "note": "On track"
        },
        {
          "task": "FLOORING: PURCHASE MATERIAL",
          "due": "Apr 21",
          "risk": "low",
          "note": "On track"
        },
        {
          "task": "CARPET: SECURE PRICING",
          "due": "Apr 21",
          "risk": "low",
          "note": "On track"
        },
        {
          "task": "COUNTERTOPS: COMPLETE TAKEOFF",
          "due": "Apr 21",
          "risk": "low",
          "note": "On track"
        },
        {
          "task": "COUNTERTOPS: CREATE SOW",
          "due": "Apr 22",
          "risk": "low",
          "note": "On track"
        },
        {
          "task": "FLOORING: PURCHASE MATERIAL (BASEBOARDS)",
          "due": "Apr 22",
          "risk": "low",
          "note": "On track"
        },
        {
          "task": "FLOORING: CREATE SOW",
          "due": "Apr 22",
          "risk": "low",
          "note": "On track"
        },
        {
          "task": "CARPET: PURCHASE MATERIAL",
          "due": "Apr 22",
          "risk": "low",
          "note": "On track"
        },
        {
          "task": "CARPET: CREATE SOW",
          "due": "Apr 22",
          "risk": "low",
          "note": "On track"
        },
        {
          "task": "COUNTERTOPS: SOURCE VENDORS",
          "due": "Apr 23",
          "risk": "low",
          "note": "On track"
        },
        {
          "task": "FLOORING: SOURCE VENDORS",
          "due": "Apr 23",
          "risk": "low",
          "note": "On track"
        },
        {
          "task": "CARPET: SOURCE VENDORS",
          "due": "Apr 23",
          "risk": "low",
          "note": "On track"
        },
        {
          "task": "COUNTERTOPS: APPROVE WO",
          "due": "Apr 24",
          "risk": "low",
          "note": "On track"
        },
        {
          "task": "FLOORING: APPROVE WO",
          "due": "Apr 24",
          "risk": "low",
          "note": "On track"
        },
        {
          "task": "CARPET: CONFIRM DELIVERY",
          "due": "Apr 24",
          "risk": "low",
          "note": "On track"
        },
        {
          "task": "CARPET: APPROVE WO",
          "due": "Apr 24",
          "risk": "low",
          "note": "On track"
        },
        {
          "task": "CABINETS: CONFIRM SCHEDULE",
          "due": "Apr 25",
          "risk": "low",
          "note": "On track"
        },
        {
          "task": "INTERIOR PAINT: PM INSPECTION / CC REPORT",
          "due": "Apr 25",
          "risk": "low",
          "note": "On track"
        },
        {
          "task": "COUNTERTOPS: CONFIRM SCHEDULE",
          "due": "Apr 25",
          "risk": "low",
          "note": "On track"
        },
        {
          "task": "FLOORING: CONFIRM SCHEDULE",
          "due": "Apr 25",
          "risk": "low",
          "note": "On track"
        },
        {
          "task": "CARPET: CONFIRM SCHEDULE",
          "due": "Apr 25",
          "risk": "low",
          "note": "On track"
        },
        {
          "task": "DRYWALL: PM INSPECTION / CC REPORT",
          "due": "Apr 27",
          "risk": "low",
          "note": "On track"
        }
      ]
    }
  ],
  "schedule_drift": {
    "total_changes": 3,
    "by_type": {
      "last_minute": 3,
      "reactive": 0,
      "proactive": 0,
      "cascade": 0
    },
    "worst_projects": [
      {
        "name": "Ginger Brown",
        "drift": "+6d"
      },
      {
        "name": "Stephanie and Marc Felton",
        "drift": "+2d"
      }
    ]
  }
}